Workbook
Name FECHA: #REF!
Name PERIODO: #REF!
Name TITULO: #REF!
Name VA: #REF!
Name VA_Ktes: #REF!

Sheet Cuadro 1
A3: Producto Interno Bruto - PIB
A5: Valores a precios corrientes
A6: Miles de millones de pesos
A7: Base 2015
A8: 2005 - 2024pr | Y8: Índice
A10: Clasificación Cuentas Nacionales | B10: Secciones CIIU Rev. 4 A.C. 12 agrupaciones | C10: Secciones y divisiones CIIU Rev. 4 A.C. 25 agrupaciones | D10: Divisiones CIIU Rev. 4 A.C. 61 agrupaciones | E10: Concepto | F10: 2005 | G10: 2006 | H10: 2007 | I10: 2008 | J10: 2009 | K10: 2010 | L10: 2011 | M10: 2012 | N10: 2013 | O10: 2014 | P10: 2015 | Q10: 2016 | R10: 2017 | S10: 2018 | T10: 2019 | U10: 2020 | V10: 2021 | W10: 2022 | X10: 2023p | Y10: 2024pr
A12: PIB enfoque de la producción
B14: A | E14: Agricultura, ganadería, caza, silvicultura y pesca | F14: 25439 | G14: 27425 | H14: 29715 | I14: 31869 | J14: 33554 | K14: 34411 | L14: 37709 | M14: 37209 | N14: 38509 | O14: 41555 | P14: 48124 | Q14: 57065 | R14: 58815 | S14: 61497 | T14: 67958 | U14: 74970 | V14: 92690 | W14: 129919 | X14: 139567 | Y14: 158406.08
C15: A | E15: Agricultura, ganadería, caza, silvicultura y pesca | F15: 25439 | G15: 27425 | H15: 29715 | I15: 31869 | J15: 33554 | K15: 34411 | L15: 37709 | M15: 37209 | N15: 38509 | O15: 41555 | P15: 48124 | Q15: 57065 | R15: 58815 | S15: 61497 | T15: 67958 | U15: 74970 | V15: 92690 | W15: 129919 | X15: 139567 | Y15: 158406.08
D16: 001 - 008, 013 | E16: Cultivos agrícolas transitorios; otros cultivos agrícolas permanentes; Propagación de plantas (actividades de viveros, excepto viveros forestales); actividades de apoyo a la agricultura y la ganadería, y posteriores a la cosecha, explotación mixta (agrícola y pecuaria) y caza ordinaria y mediante trampas y actividades de servicios conexas | F16: 13312 | G16: 14490 | H16: 15675 | I16: 17044 | J16: 18522 | K16: 18653 | L16: 20760 | M16: 20538 | N16: 20723 | O16: 22133 | P16: 27339 | Q16: 33033 | R16: 33979 | S16: 36116 | T16: 40735 | U16: 44817 | V16: 53191 | W16: 80655 | X16: 87726 | Y16: 99008.74
D17: 003 | E17: Cultivo permanente de café | F17: 2763 | G17: 3039 | H17: 3195 | I17: 3140 | J17: 2986 | K17: 3810 | L17: 4453 | M17: 3254 | N17: 4067 | O17: 4659 | P17: 5299 | Q17: 6299 | R17: 6482 | S17: 6173 | T17: 7310 | U17: 8105 | V17: 11273 | W17: 14406 | X17: 12865 | Y17: 19384.83
D18: 009 - 012 | E18: Ganadería | F18: 7843 | G18: 8223 | H18: 9043 | I18: 9815 | J18: 10043 | K18: 9931 | L18: 10392 | M18: 11091 | N18: 11238 | O18: 11910 | P18: 12265 | Q18: 14098 | R18: 14639 | S18: 15224 | T18: 15735 | U18: 16980 | V18: 21931 | W18: 27215 | X18: 30322 | Y18: 30870.41
D19: 014, 015 | E19: Silvicultura y extracción de madera | F19: 854 | G19: 915 | H19: 984 | I19: 1011 | J19: 1109 | K19: 1127 | L19: 1197 | M19: 1352 | N19: 1493 | O19: 1617 | P19: 1796 | Q19: 1963 | R19: 2047 | S19: 2075 | T19: 2201 | U19: 2332 | V19: 2986 | W19: 3289 | X19: 3877 | Y19: 3895.9
D20: 016 | E20: Pesca y acuicultura | F20: 667 | G20: 758 | H20: 818 | I20: 859 | J20: 894 | K20: 890 | L20: 907 | M20: 974 | N20: 988 | O20: 1236 | P20: 1425 | Q20: 1672 | R20: 1668 | S20: 1909 | T20: 1977 | U20: 2736 | V20: 3309 | W20: 4354 | X20: 4777 | Y20: 5246.21
B21: B | E21: Explotación de minas y canteras | F21: 22071 | G21: 26127 | H21: 26443 | I21: 38675 | J21: 37234 | K21: 47105 | L21: 70548 | M21: 74557 | N21: 73340 | O21: 64274 | P21: 47627 | Q21: 40999 | R21: 47538 | S21: 57788 | T21: 58317 | U21: 40689 | V21: 64235 | W21: 107532 | X21: 89489 | Y21: 75886.25
C22: B | E22: Explotación de minas y canteras | F22: 22071 | G22: 26127 | H22: 26443 | I22: 38675 | J22: 37234 | K22: 47105 | L22: 70548 | M22: 74557 | N22: 73340 | O22: 64274 | P22: 47627 | Q22: 40999 | R22: 47538 | S22: 57788 | T22: 58317 | U22: 40689 | V22: 64235 | W22: 107532 | X22: 89489 | Y22: 75886.25
D23: 017 | E23: Extracción de carbón de piedra y lignito | F23: 4915 | G23: 5705 | H23: 5577 | I23: 8542 | J23: 8610 | K23: 8621 | L23: 11256 | M23: 10973 | N23: 9303 | O23: 8404 | P23: 8833 | Q23: 11027 | R23: 13634 | S23: 15167 | T23: 12226 | U23: 7429 | V23: 15146 | W23: 37050 | X23: 26365 | Y23: 16021.16
D24: 018, 021 | E24: Extracción de petróleo crudo y gas natural y actividades de apoyo para la extracción de petróleo y de gas natural | F24: 14038 | G24: 15969 | H24: 15526 | I24: 25915 | J24: 24058 | K24: 33071 | L24: 53113 | M24: 56982 | N24: 58714 | O24: 50497 | P24: 32852 | Q24: 22289 | R24: 27822 | S24: 36871 | T24: 39127 | U24: 24320 | V24: 38429 | W24: 58383 | X24: 49629 | Y24: 45363.31
D25: 019 | E25: Extracción de minerales metalíferos | F25: 2143 | G25: 3275 | H25: 3999 | I25: 2706 | J25: 2994 | K25: 3917 | L25: 4448 | M25: 4754 | N25: 3313 | O25: 3131 | P25: 3592 | Q25: 5001 | R25: 3472 | S25: 3112 | T25: 4163 | U25: 6849 | V25: 8125 | W25: 9210 | X25: 10433 | Y25: 11217.77
D26: 020 | E26: Extracción de otras minas y canteras | F26: 865 | G26: 1046 | H26: 1197 | I26: 1352 | J26: 1406 | K26: 1317 | L26: 1511 | M26: 1625 | N26: 1825 | O26: 2067 | P26: 2156 | Q26: 2435 | R26: 2421 | S26: 2437 | T26: 2628 | U26: 1932 | V26: 2292 | W26: 2464 | X26: 2712 | Y26: 2982.66
D27: 022 | E27: Actividades de apoyo para otras actividades de explotación de minas y canteras | F27: 110 | G27: 132 | H27: 144 | I27: 160 | J27: 166 | K27: 179 | L27: 220 | M27: 223 | N27: 185 | O27: 175 | P27: 194 | Q27: 247 | R27: 189 | S27: 201 | T27: 173 | U27: 159 | V27: 243 | W27: 425 | X27: 350 | Y27: 301.35
B28: C | E28: Industrias manufactureras | F28: 54043 | G28: 60975 | H28: 69222 | I28: 73264 | J28: 74133 | K28: 75989 | L28: 81820 | M28: 87241 | N28: 90421 | O28: 93603 | P28: 99789 | Q28: 106226 | R28: 105022 | S28: 110157 | T28: 115830 | U28: 107111 | V28: 133565 | W28: 163991 | X28: 172226 | Y28: 172275.15
C29: C01 | E29: Elaboración de productos alimenticios; elaboración de bebidas; elaboración de productos de tabaco | F29: 16767 | G29: 18095 | H29: 20270 | I29: 22528 | J29: 24071 | K29: 23065 | L29: 24019 | M29: 24776 | N29: 25438 | O29: 26163 | P29: 27219 | Q29: 30138 | R29: 30603 | S29: 31305 | T29: 31682 | U29: 32205 | V29: 39352 | W29: 49066 | X29: 51605 | Y29: 51899.4
D30: 023 - 025 | E30: Procesamiento y conservación de carne y productos cárnicos de bovinos, bufalinos, porcinos y otras carnes n.c.p.; procesamiento y conservación de carne y productos cárnicos de aves de corral y procesamiento y conservación de pescados, crustáceos y moluscos | F30: 3222 | G30: 3345 | H30: 3920 | I30: 4568 | J30: 4835 | K30: 4566 | L30: 4830 | M30: 4997 | N30: 5232 | O30: 5475 | P30: 5896 | Q30: 6543 | R30: 6579 | S30: 6924 | T30: 7112 | U30: 7595 | V30: 10228 | W30: 12957 | X30: 14058 | Y30: 14783.27
D31: 026 | E31: Elaboración de aceites y grasas de origen vegetal y animal | F31: 1255 | G31: 1165 | H31: 1284 | I31: 1456 | J31: 1467 | K31: 1420 | L31: 1483 | M31: 1271 | N31: 1093 | O31: 1373 | P31: 1506 | Q31: 1986 | R31: 1884 | S31: 1715 | T31: 1570 | U31: 1443 | V31: 2848 | W31: 3596 | X31: 3011 | Y31: 2630.82
D32: 027 | E32: Elaboración de productos lácteos | F32: 1916 | G32: 1989 | H32: 2188 | I32: 2460 | J32: 2464 | K32: 2528 | L32: 2722 | M32: 2962 | N32: 3095 | O32: 3131 | P32: 3217 | Q32: 3421 | R32: 3553 | S32: 3609 | T32: 3644 | U32: 3863 | V32: 3954 | W32: 4851 | X32: 5388 | Y32: 5307.38
D33: 028, 032, 035 | E33: Elaboración de productos de molinería, almidones y productos derivados del almidón; elaboración de productos de panadería; elaboración de macarrones, fideos, alcuzcuz, y productos farináceos similares y elaboración de alimentos preparados para animales | F33: 3057 | G33: 3110 | H33: 3581 | I33: 4238 | J33: 4290 | K33: 3893 | L33: 3961 | M33: 4139 | N33: 4229 | O33: 3970 | P33: 3922 | Q33: 4737 | R33: 4560 | S33: 4682 | T33: 5156 | U33: 6021 | V33: 6488 | W33: 8502 | X33: 8399 | Y33: 7687.59
D34: 029 | E34: Elaboración de productos de café | F34: 894 | G34: 795 | H34: 637 | I34: 587 | J34: 503 | K34: 465 | L34: 373 | M34: 402 | N34: 501 | O34: 517 | P34: 702 | Q34: 625 | R34: 702 | S34: 651 | T34: 722 | U34: 282 | V34: 386 | W34: 488 | X34: 455 | Y34: 613.7
D35: 030, 031 | E35: Elaboración de azúcar y elaboración de panela | F35: 1509 | G35: 2220 | H35: 2107 | I35: 2156 | J35: 2742 | K35: 2945 | L35: 3339 | M35: 2712 | N35: 2386 | O35: 2516 | P35: 2618 | Q35: 2793 | R35: 3066 | S35: 3060 | T35: 2656 | U35: 3039 | V35: 3502 | W35: 4101 | X35: 4205 | Y35: 4228.68
D36: 033 | E36: Elaboración de cacao, chocolate y productos de confitería | F36: 620 | G36: 641 | H36: 675 | I36: 745 | J36: 748 | K36: 677 | L36: 721 | M36: 790 | N36: 760 | O36: 747 | P36: 688 | Q36: 635 | R36: 665 | S36: 702 | T36: 756 | U36: 726 | V36: 859 | W36: 1077 | X36: 1175 | Y36: 1209.29
D37: 034 | E37: Procesamiento y conservación de frutas, legumbres, hortalizas y tubérculos; elaboración de otros productos alimenticios (platos preparados y conservados mediante enlatado o congelado, elaboración de sopas y caldos en estado sólidos, polvo o instantáneas entre otros) | F37: 1064 | G37: 1179 | H37: 1397 | I37: 1531 | J37: 1657 | K37: 1548 | L37: 1483 | M37: 1795 | N37: 1997 | O37: 1986 | P37: 2276 | Q37: 2333 | R37: 2398 | S37: 2453 | T37: 2520 | U37: 2640 | V37: 2985 | W37: 3652 | X37: 3826 | Y37: 3832.14
D38: 036 | E38: Elaboración de bebidas (incluido el hielo) y elaboración de productos de tabaco | F38: 3230 | G38: 3651 | H38: 4481 | I38: 4787 | J38: 5365 | K38: 5023 | L38: 5107 | M38: 5708 | N38: 6145 | O38: 6448 | P38: 6394 | Q38: 7065 | R38: 7196 | S38: 7509 | T38: 7546 | U38: 6596 | V38: 8102 | W38: 9842 | X38: 11088 | Y38: 11606.53
C39: C02 | E39: Fabricación de productos textiles; confección de prendas de vestir; curtido y recurtido de cueros; fabricación de calzado; fabricación de artículos de viaje, maletas, bolsos de mano y artículos similares, y fabricación de artículos de talabartería y guarnicionería; adobo y teñido de pieles | F39: 6783 | G39: 7663 | H39: 9159 | I39: 9358 | J39: 8140 | K39: 8263 | L39: 9078 | M39: 9671 | N39: 9964 | O39: 9996 | P39: 10343 | Q39: 10806 | R39: 10409 | S39: 10412 | T39: 11174 | U39: 8370 | V39: 12307 | W39: 14664 | X39: 14168 | Y39: 14049.38
D40: 037, 038 | E40: Preparación, hilatura, tejeduría y acabado de productos textiles; fabricación de otros productos textiles, Confección de prendas de vestir | F40: 5597 | G40: 6382 | H40: 7553 | I40: 7511 | J40: 6618 | K40: 6799 | L40: 7455 | M40: 7958 | N40: 8243 | O40: 8280 | P40: 8584 | Q40: 8992 | R40: 8771 | S40: 8912 | T40: 9718 | U40: 7554 | V40: 11114 | W40: 13277 | X40: 12784 | Y40: 12711.32
D41: 039 | E41: Curtido y recurtido de cueros; fabricación de calzado; fabricación de artículos de viaje, maletas, bolsos de mano y artículos similares, y fabricación de artículos de talabartería y guarnicionería; adobo y teñido de pieles | F41: 1186 | G41: 1281 | H41: 1606 | I41: 1847 | J41: 1522 | K41: 1464 | L41: 1623 | M41: 1713 | N41: 1721 | O41: 1716 | P41: 1759 | Q41: 1814 | R41: 1638 | S41: 1500 | T41: 1456 | U41: 816 | V41: 1193 | W41: 1387 | X41: 1384 | Y41: 1338.06
C42: C03 | E42: Transformación de la madera y fabricación de productos de madera y de corcho, excepto muebles; fabricación de artículos de cestería y espartería; fabricación de papel, cartón y productos de papel y de cartón; actividades de impresión; producción de copias a partir de grabaciones originales | F42: 3401 | G42: 3842 | H42: 4338 | I42: 4616 | J42: 4892 | K42: 4662 | L42: 4773 | M42: 5123 | N42: 5273 | O42: 5403 | P42: 6057 | Q42: 5931 | R42: 5798 | S42: 5961 | T42: 6293 | U42: 6124 | V42: 6721 | W42: 8706 | X42: 8875 | Y42: 8922.24
D43: 040 | E43: Transformación de la madera y fabricación de productos de madera y de corcho, excepto muebles; fabricación de artículos de cestería y espartería | F43: 531 | G43: 645 | H43: 834 | I43: 908 | J43: 903 | K43: 938 | L43: 961 | M43: 996 | N43: 1039 | O43: 1094 | P43: 1137 | Q43: 1170 | R43: 1092 | S43: 1036 | T43: 1010 | U43: 973 | V43: 935 | W43: 1168 | X43: 1137 | Y43: 1114.62
D44: 041 | E44: Fabricación de papel, cartón y productos de papel y de cartón | F44: 1977 | G44: 2187 | H44: 2356 | I44: 2478 | J44: 2653 | K44: 2350 | L44: 2318 | M44: 2523 | N44: 2581 | O44: 2655 | P44: 3219 | Q44: 3115 | R44: 3269 | S44: 3479 | T44: 3818 | U44: 3764 | V44: 4244 | W44: 5629 | X44: 5798 | Y44: 5847.87
D45: 042 | E45: Actividades de impresión; producción de copias a partir de grabaciones originales (Copia a partir de un original en CD, DVD, Bluray) | F45: 893 | G45: 1010 | H45: 1148 | I45: 1230 | J45: 1336 | K45: 1374 | L45: 1494 | M45: 1604 | N45: 1653 | O45: 1654 | P45: 1701 | Q45: 1646 | R45: 1437 | S45: 1446 | T45: 1465 | U45: 1387 | V45: 1542 | W45: 1909 | X45: 1940 | Y45: 1959.76
C46: C04 | E46: Coquización, fabricación de productos de la refinación del petróleo y actividad de mezcla de combustibles; fabricación de sustancias y productos químicos; fabricación de productos farmacéuticos, sustancias químicas medicinales y productos botánicos de uso farmacéutico; fabricación de productos de caucho y de plástico; fabricación de otros productos minerales no metálicos | F46: 15277 | G46: 17718 | H46: 20014 | I46: 21641 | J46: 21960 | K46: 23509 | L46: 26517 | M46: 28334 | N46: 30322 | O46: 32235 | P46: 35555 | Q46: 38111 | R46: 39071 | S46: 42105 | T46: 44731 | U46: 40040 | V46: 50786 | W46: 61741 | X46: 67520 | Y46: 66953.1
D47: 043, 044 | E47: Coquización, fabricación de productos de la refinación del petróleo y actividades de mezcla de combustibles | F47: 2798 | G47: 3398 | H47: 4003 | I47: 4580 | J47: 3925 | K47: 4983 | L47: 6422 | M47: 6632 | N47: 6925 | O47: 7357 | P47: 7761 | Q47: 8485 | R47: 10669 | S47: 12991 | T47: 14360 | U47: 10282 | V47: 15096 | W47: 19424 | X47: 22810 | Y47: 22944.59
D48: 045 - 047 | E48: Fabricación de sustancias químicas básicas, abonos y compuestos inorgánicos nitrogenados, plásticos y caucho sintético en formas primarias; fabricación de otros productos químicos; fabricación de fibras sintéticas y artificiales; fabricación de productos farmacéuticos, sustancias químicas medicinales y productos botánicos de uso farmacéutico | F48: 5776 | G48: 6511 | H48: 7102 | I48: 7704 | J48: 8434 | K48: 9017 | L48: 9279 | M48: 9573 | N48: 10402 | O48: 10571 | P48: 11814 | Q48: 13456 | R48: 13597 | S48: 14233 | T48: 15085 | U48: 16079 | V48: 20226 | W48: 24107 | X48: 25644 | Y48: 25480.03
D49: 048 | E49: Fabricación de productos de caucho y de plástico | F49: 2104 | G49: 2287 | H49: 2457 | I49: 2529 | J49: 2494 | K49: 2400 | L49: 2483 | M49: 2742 | N49: 2676 | O49: 2491 | P49: 2791 | Q49: 2869 | R49: 2735 | S49: 2963 | T49: 3196 | U49: 3173 | V49: 3246 | W49: 3802 | X49: 3662 | Y49: 3634.55
D50: 049 | E50: Fabricación de otros productos minerales no metálicos | F50: 4599 | G50: 5522 | H50: 6452 | I50: 6828 | J50: 7107 | K50: 7109 | L50: 8333 | M50: 9387 | N50: 10319 | O50: 11816 | P50: 13189 | Q50: 13301 | R50: 12070 | S50: 11918 | T50: 12090 | U50: 10506 | V50: 12218 | W50: 14408 | X50: 15404 | Y50: 14893.93
C51: C05 | E51: Fabricación de productos metalúrgicos básicos; fabricación de productos elaborados de metal, excepto maquinaria y equipo; fabricación de aparatos y equipo eléctrico; fabricación de productos informáticos, electrónicos y ópticos; fabricación de maquinaria y equipo n.c.p.; fabricación de vehículos automotores, remolques y semirremolques; fabricación de otros tipos de equipo de transporte; instalación, mantenimiento y reparación especializado de maquinaria y equipo | F51: 8705 | G51: 10168 | H51: 11660 | I51: 11144 | J51: 11017 | K51: 12285 | L51: 13046 | M51: 14636 | N51: 14474 | O51: 14661 | P51: 15004 | Q51: 15651 | R51: 13681 | S51: 14627 | T51: 16176 | U51: 15025 | V51: 17710 | W51: 21700 | X51: 21895 | Y51: 22271.12
D52: 050, 051 | E52: Fabricación de productos metalúrgicos básicos; fabricación de productos elaborados de metal, excepto maquinaria y equipo | F52: 2221 | G52: 2742 | H52: 3074 | I52: 3553 | J52: 3701 | K52: 4319 | L52: 5185 | M52: 5739 | N52: 5375 | O52: 5703 | P52: 5946 | Q52: 6329 | R52: 6208 | S52: 6688 | T52: 7671 | U52: 8183 | V52: 9839 | W52: 11746 | X52: 11532 | Y52: 11709.61
D53: 052 | E53: Fabricación de aparatos y equipo eléctrico; fabricación de productos informáticos, electrónicos y ópticos | F53: 1263 | G53: 1523 | H53: 1776 | I53: 1777 | J53: 1727 | K53: 1827 | L53: 1717 | M53: 1718 | N53: 1792 | O53: 1729 | P53: 1920 | Q53: 2122 | R53: 1960 | S53: 2111 | T53: 2227 | U53: 2174 | V53: 2376 | W53: 2884 | X53: 3308 | Y53: 3522.08
D54: 053, 057 | E54: Fabricación de maquinaria y equipo n.c.p.; instalación, mantenimiento y reparación especializado de maquinaria y equipo | F54: 3273 | G54: 3615 | H54: 4002 | I54: 4043 | J54: 4025 | K54: 3893 | L54: 4048 | M54: 4439 | N54: 4691 | O54: 4504 | P54: 4635 | Q54: 4669 | R54: 3237 | S54: 3351 | T54: 3560 | U54: 3087 | V54: 3271 | W54: 4033 | X54: 4257 | Y54: 4375.88
D55: 054 | E55: Fabricación de vehículos automotores, remolques y semirremolques; fabricación de otros tipos de equipo de transporte | F55: 1948 | G55: 2288 | H55: 2808 | I55: 1771 | J55: 1564 | K55: 2246 | L55: 2096 | M55: 2740 | N55: 2616 | O55: 2725 | P55: 2503 | Q55: 2531 | R55: 2276 | S55: 2477 | T55: 2718 | U55: 1581 | V55: 2224 | W55: 3037 | X55: 2798 | Y55: 2663.55
C56: C06 | E56: Fabricación de muebles, colchones y somieres; otras industrias manufactureras | F56: 3110 | G56: 3489 | H56: 3781 | I56: 3977 | J56: 4053 | K56: 4205 | L56: 4387 | M56: 4701 | N56: 4950 | O56: 5145 | P56: 5611 | Q56: 5589 | R56: 5460 | S56: 5747 | T56: 5774 | U56: 5347 | V56: 6689 | W56: 8114 | X56: 8163 | Y56: 8179.91
D57: 055 | E57: Fabricación de muebles, colchones y somieres | F57: 1280 | G57: 1402 | H57: 1576 | I57: 1658 | J57: 1781 | K57: 1741 | L57: 1837 | M57: 1986 | N57: 2132 | O57: 2209 | P57: 2306 | Q57: 2321 | R57: 2195 | S57: 2259 | T57: 2295 | U57: 2035 | V57: 2730 | W57: 3099 | X57: 3092 | Y57: 3012.11
D58: 056 | E58: Otras industrias manufactureras | F58: 1830 | G58: 2087 | H58: 2205 | I58: 2319 | J58: 2272 | K58: 2464 | L58: 2550 | M58: 2715 | N58: 2818 | O58: 2936 | P58: 3305 | Q58: 3268 | R58: 3265 | S58: 3488 | T58: 3479 | U58: 3312 | V58: 3959 | W58: 5015 | X58: 5071 | Y58: 5167.79
B59: D + E | E59: Suministro de electricidad, gas, vapor y aire acondicionado; Distribución de agua; evacuación y tratamiento de aguas residuales, gestión de desechos y actividades de saneamiento ambiental | F59: 12035 | G59: 13290 | H59: 14757 | I59: 15895 | J59: 16341 | K59: 17809 | L59: 19318 | M59: 20467 | N59: 21767 | O59: 22947 | P59: 24599 | Q59: 27624 | R59: 29789 | S59: 32616 | T59: 36124 | U59: 38850 | V59: 44820 | W59: 54995 | X59: 65346 | Y59: 74106.13
C60: D | E60: Suministro de electricidad, gas, vapor y aire acondicionado | F60: 7381 | G60: 8177 | H60: 9188 | I60: 10139 | J60: 10357 | K60: 11414 | L60: 12551 | M60: 13579 | N60: 14622 | O60: 15611 | P60: 16842 | Q60: 19583 | R60: 20665 | S60: 22595 | T60: 25137 | U60: 27894 | V60: 31650 | W60: 39804 | X60: 49309 | Y60: 57328.68
D61: 058 - 060 | E61: Generación de energía eléctrica; transmisión de energía eléctrica y distribución y comercialización de energía eléctrica | F61: 6293 | G61: 6800 | H61: 7488 | I61: 8117 | J61: 8965 | K61: 9896 | L61: 10879 | M61: 11661 | N61: 12520 | O61: 13439 | P61: 14017 | Q61: 16085 | R61: 16795 | S61: 18461 | T61: 20639 | U61: 22880 | V61: 26007 | W61: 33079 | X61: 42061 | Y61: 49700.73
D62: 061 | E62: Producción de gas; distribución de combustibles gaseosos por tuberías; suministro de vapor y aire acondicionado | F62: 1088 | G62: 1377 | H62: 1700 | I62: 2022 | J62: 1392 | K62: 1518 | L62: 1672 | M62: 1918 | N62: 2102 | O62: 2172 | P62: 2825 | Q62: 3498 | R62: 3870 | S62: 4134 | T62: 4498 | U62: 5014 | V62: 5643 | W62: 6725 | X62: 7248 | Y62: 7627.95
C63: E | E63: Distribución de agua; evacuación y tratamiento de aguas residuales, gestión de desechos y actividades de saneamiento ambiental | F63: 4654 | G63: 5113 | H63: 5569 | I63: 5756 | J63: 5984 | K63: 6395 | L63: 6767 | M63: 6888 | N63: 7145 | O63: 7336 | P63: 7757 | Q63: 8041 | R63: 9124 | S63: 10021 | T63: 10987 | U63: 10956 | V63: 13170 | W63: 15191 | X63: 16037 | Y63: 16777.45
D64: 062 | E64: Captación, tratamiento y distribución de agua | F64: 1463 | G64: 1488 | H64: 1578 | I64: 1736 | J64: 1785 | K64: 1854 | L64: 1962 | M64: 2079 | N64: 2178 | O64: 2268 | P64: 2376 | Q64: 2502 | R64: 2703 | S64: 3012 | T64: 3263 | U64: 3372 | V64: 3585 | W64: 3898 | X64: 4499 | Y64: 4795.56
D65: 063, 064, 066 | E65: Evacuación y tratamiento de aguas residuales; recolección, tratamiento y disposición de desechos y actividades de saneamiento ambiental y otros servicios de gestión de desechos | F65: 2227 | G65: 2561 | H65: 2831 | I65: 2980 | J65: 3175 | K65: 3391 | L65: 3520 | M65: 3600 | N65: 3739 | O65: 3913 | P65: 4068 | Q65: 4223 | R65: 4941 | S65: 5448 | T65: 6159 | U65: 5983 | V65: 6554 | W65: 7467 | X65: 8660 | Y65: 9238.73
D66: 065 | E66: Recuperación de materiales (reciclaje) | F66: 964 | G66: 1064 | H66: 1160 | I66: 1040 | J66: 1024 | K66: 1150 | L66: 1285 | M66: 1209 | N66: 1228 | O66: 1155 | P66: 1313 | Q66: 1316 | R66: 1480 | S66: 1561 | T66: 1565 | U66: 1601 | V66: 3031 | W66: 3826 | X66: 2878 | Y66: 2743.17
B67: F | E67: Construcción | F67: 14415 | G67: 17575 | H67: 20611 | I67: 25288 | J67: 29019 | K67: 29776 | L67: 34462 | M67: 40385 | N67: 48320 | O67: 55568 | P67: 58042 | Q67: 64325 | R67: 64474 | S67: 65110 | T67: 65277 | U67: 47384 | V67: 50235 | W67: 57772 | X67: 64208 | Y67: 71252.62
C68: F01 | E68: Construcción de edificaciones residenciales y no residenciales | F68: 7615 | G68: 9167 | H68: 10406 | I68: 13136 | J68: 14529 | K68: 15180 | L68: 17192 | M68: 20614 | N68: 24987 | O68: 28539 | P68: 30111 | Q68: 33869 | R68: 31692 | S68: 32115 | T68: 30015 | U68: 21637 | V68: 23788 | W68: 29057 | X68: 33644 | Y68: 36367.77
D69: 067 | E69: Construcción de edificaciones residenciales y no residenciales | F69: 7615 | G69: 9167 | H69: 10406 | I69: 13136 | J69: 14529 | K69: 15180 | L69: 17192 | M69: 20614 | N69: 24987 | O69: 28539 | P69: 30111 | Q69: 33869 | R69: 31692 | S69: 32115 | T69: 30015 | U69: 21637 | V69: 23788 | W69: 29057 | X69: 33644 | Y69: 36367.77
C70: F02 | E70: Construcción de carreteras y vías de ferrocarril, de proyectos de servicio público y de otras obras de ingeniería civil | F70: 4321 | G70: 5324 | H70: 6617 | I70: 7476 | J70: 9233 | K70: 9014 | L70: 10844 | M70: 11809 | N70: 13444 | O70: 15449 | P70: 15906 | Q70: 15742 | R70: 17086 | S70: 16946 | T70: 20046 | U70: 15359 | V70: 14837 | W70: 15677 | X70: 15622 | Y70: 18331.93
D71: 068 | E71: Construcción de carreteras y vías de ferrocarril, de proyectos de servicio público y de otras obras de ingeniería civil | F71: 4321 | G71: 5324 | H71: 6617 | I71: 7476 | J71: 9233 | K71: 9014 | L71: 10844 | M71: 11809 | N71: 13444 | O71: 15449 | P71: 15906 | Q71: 15742 | R71: 17086 | S71: 16946 | T71: 20046 | U71: 15359 | V71: 14837 | W71: 15677 | X71: 15622 | Y71: 18331.93
C72: F03 | E72: Actividades especializadas para la construcción de edificaciones y obras de ingeniería civil (Alquiler de maquinaría y equipo de construcción con operadores) | F72: 2479 | G72: 3084 | H72: 3588 | I72: 4676 | J72: 5257 | K72: 5582 | L72: 6426 | M72: 7962 | N72: 9889 | O72: 11580 | P72: 12025 | Q72: 14714 | R72: 15696 | S72: 16049 | T72: 15216 | U72: 10388 | V72: 11610 | W72: 13038 | X72: 14942 | Y72: 16552.92
D73: 069 | E73: Actividades especializadas para la construcción de edificaciones y obras de ingeniería civil (Alquiler de maquinaría y equipo de construcción con operadores) | F73: 2479 | G73: 3084 | H73: 3588 | I73: 4676 | J73: 5257 | K73: 5582 | L73: 6426 | M73: 7962 | N73: 9889 | O73: 11580 | P73: 12025 | Q73: 14714 | R73: 15696 | S73: 16049 | T73: 15216 | U73: 10388 | V73: 11610 | W73: 13038 | X73: 14942 | Y73: 16552.92
B74: G + H + I | E74: Comercio al por mayor y al por menor; reparación de vehículos automotores y motocicletas; Transporte y almacenamiento; Alojamiento y servicios de comida | F74: 54918 | G74: 62152 | H74: 71392 | I74: 75636 | J74: 79703 | K74: 84926 | L74: 93024 | M74: 98508 | N74: 109807 | O74: 120677 | P74: 135429 | Q74: 152684 | R74: 163052 | S74: 173708 | T74: 188266 | U74: 170072 | V74: 216640 | W74: 272982 | X74: 296770 | Y74: 322958.11
C75: G | E75: Comercio al por mayor y al por menor; reparación de vehículos automotores y motocicletas | F75: 30086 | G75: 33669 | H75: 37676 | I75: 39765 | J75: 40366 | K75: 42670 | L75: 47656 | M75: 49371 | N75: 53123 | O75: 56951 | P75: 64866 | Q75: 75403 | R75: 81148 | S75: 86706 | T75: 96445 | U75: 97793 | V75: 122888 | W75: 149841 | X75: 158342 | Y75: 174980.39
D76: 070 | E76: Comercio al por mayor y en comisión o por contrata; comercio al por menor (incluso el comercio al por menor de combustibles); comercio de vehículos automotores y motocicletas, sus partes, piezas y accesorios | F76: 27744 | G76: 31105 | H76: 34836 | I76: 36752 | J76: 36881 | K76: 38835 | L76: 43635 | M76: 44851 | N76: 48295 | O76: 51729 | P76: 59399 | Q76: 69415 | R76: 74479 | S76: 79555 | T76: 88906 | U76: 91306 | V76: 114850 | W76: 140325 | X76: 147836 | Y76: 163540.66
D77: 071 | E77: Mantenimiento y reparación de vehículos automotores y motocicletas | F77: 2342 | G77: 2564 | H77: 2840 | I77: 3013 | J77: 3485 | K77: 3835 | L77: 4021 | M77: 4520 | N77: 4828 | O77: 5222 | P77: 5467 | Q77: 5988 | R77: 6669 | S77: 7151 | T77: 7539 | U77: 6487 | V77: 8038 | W77: 9516 | X77: 10506 | Y77: 11439.73
C78: H | E78: Transporte y almacenamiento | F78: 15707 | G78: 17967 | H78: 21054 | I78: 21696 | J78: 23593 | K78: 24337 | L78: 25612 | M78: 26657 | N78: 31562 | O78: 35968 | P78: 40703 | Q78: 44048 | R78: 45355 | S78: 48742 | T78: 51518 | U78: 42606 | V78: 51497 | W78: 66933 | X78: 74883 | Y78: 80387
D79: 072, 074 | E79: Transporte terrestre y transporte por tuberías | F79: 11428 | G79: 12781 | H79: 15196 | I79: 15364 | J79: 16958 | K79: 17520 | L79: 17887 | M79: 18308 | N79: 22011 | O79: 25313 | P79: 27868 | Q79: 30597 | R79: 31526 | S79: 33541 | T79: 35002 | U79: 30817 | V79: 35866 | W79: 44863 | X79: 51108 | Y79: 54995.39
D80: 073 | E80: Transporte acuático | F80: 193 | G80: 209 | H80: 252 | I80: 289 | J80: 286 | K80: 243 | L80: 194 | M80: 166 | N80: 186 | O80: 220 | P80: 231 | Q80: 286 | R80: 309 | S80: 321 | T80: 333 | U80: 291 | V80: 304 | W80: 355 | X80: 408 | Y80: 370.93
D81: 075 | E81: Transporte aéreo | F81: 1393 | G81: 1741 | H81: 1997 | I81: 2135 | J81: 2292 | K81: 2361 | L81: 2598 | M81: 2776 | N81: 3340 | O81: 3790 | P81: 4647 | Q81: 4498 | R81: 4231 | S81: 4875 | T81: 5303 | U81: 2571 | V81: 3397 | W81: 6488 | X81: 7698 | Y81: 7397.34
D82: 076 | E82: Almacenamiento y actividades complementarias al transporte | F82: 2207 | G82: 2679 | H82: 2978 | I82: 3240 | J82: 3387 | K82: 3513 | L82: 4206 | M82: 4650 | N82: 5215 | O82: 5804 | P82: 7055 | Q82: 7727 | R82: 8304 | S82: 8927 | T82: 9674 | U82: 7666 | V82: 10471 | W82: 13567 | X82: 13930 | Y82: 15666.03
D83: 077 | E83: Actividades de correo y de servicios de mensajería | F83: 486 | G83: 557 | H83: 631 | I83: 668 | J83: 670 | K83: 700 | L83: 727 | M83: 757 | N83: 810 | O83: 841 | P83: 902 | Q83: 940 | R83: 985 | S83: 1078 | T83: 1206 | U83: 1261 | V83: 1459 | W83: 1660 | X83: 1739 | Y83: 1957.31
C84: I | E84: Alojamiento y servicios de comida | F84: 9125 | G84: 10516 | H84: 12662 | I84: 14175 | J84: 15744 | K84: 17919 | L84: 19756 | M84: 22480 | N84: 25122 | O84: 27758 | P84: 29860 | Q84: 33233 | R84: 36549 | S84: 38260 | T84: 40303 | U84: 29673 | V84: 42255 | W84: 56208 | X84: 63545 | Y84: 67590.72
D85: 078 - 080 | E85: Alojamiento y servicios de comida | F85: 9125 | G85: 10516 | H85: 12662 | I85: 14175 | J85: 15744 | K85: 17919 | L85: 19756 | M85: 22480 | N85: 25122 | O85: 27758 | P85: 29860 | Q85: 33233 | R85: 36549 | S85: 38260 | T85: 40303 | U85: 29673 | V85: 42255 | W85: 56208 | X85: 63545 | Y85: 67590.72
B86: J | E86: Información y comunicaciones | F86: 12273 | G86: 14006 | H86: 15925 | I86: 17124 | J86: 17580 | K86: 18572 | L86: 19612 | M86: 20702 | N86: 22092 | O86: 23336 | P86: 23961 | Q86: 25122 | R86: 26821 | S86: 28348 | T86: 29381 | U86: 28902 | V86: 32341 | W86: 36129 | X86: 37915 | Y86: 38682.65
C87: J | E87: Información y comunicaciones | F87: 12273 | G87: 14006 | H87: 15925 | I87: 17124 | J87: 17580 | K87: 18572 | L87: 19612 | M87: 20702 | N87: 22092 | O87: 23336 | P87: 23961 | Q87: 25122 | R87: 26821 | S87: 28348 | T87: 29381 | U87: 28902 | V87: 32341 | W87: 36129 | X87: 37915 | Y87: 38682.65
D88: 081 - 084 | E88: Información y comunicaciones | F88: 12273 | G88: 14006 | H88: 15925 | I88: 17124 | J88: 17580 | K88: 18572 | L88: 19612 | M88: 20702 | N88: 22092 | O88: 23336 | P88: 23961 | Q88: 25122 | R88: 26821 | S88: 28348 | T88: 29381 | U88: 28902 | V88: 32341 | W88: 36129 | X88: 37915 | Y88: 38682.65
B89: K | E89: Actividades financieras y de seguros | F89: 11846 | G89: 12480 | H89: 14894 | I89: 17984 | J89: 19552 | K89: 21396 | L89: 24357 | M89: 27533 | N89: 29619 | O89: 31839 | P89: 34696 | Q89: 34324 | R89: 39060 | S89: 42627 | T89: 46984 | U89: 48808 | V89: 52653 | W89: 56900 | X89: 62862 | Y89: 70547.51
C90: K | E90: Actividades financieras y de seguros | F90: 11846 | G90: 12480 | H90: 14894 | I90: 17984 | J90: 19552 | K90: 21396 | L90: 24357 | M90: 27533 | N90: 29619 | O90: 31839 | P90: 34696 | Q90: 34324 | R90: 39060 | S90: 42627 | T90: 46984 | U90: 48808 | V90: 52653 | W90: 56900 | X90: 62862 | Y90: 70547.51
D91: 085 - 088 | E91: Actividades financieras y de seguros | F91: 11846 | G91: 12480 | H91: 14894 | I91: 17984 | J91: 19552 | K91: 21396 | L91: 24357 | M91: 27533 | N91: 29619 | O91: 31839 | P91: 34696 | Q91: 34324 | R91: 39060 | S91: 42627 | T91: 46984 | U91: 48808 | V91: 52653 | W91: 56900 | X91: 62862 | Y91: 70547.51
B92: L | E92: Actividades inmobiliarias | F92: 32556 | G92: 35921 | H92: 39056 | I92: 42236 | J92: 45858 | K92: 49355 | L92: 52966 | M92: 56928 | N92: 60922 | O92: 65194 | P92: 69825 | Q92: 75645 | R92: 80976 | S92: 86825 | T92: 92388 | U92: 95042 | V92: 98900 | W92: 104886 | X92: 114270 | Y92: 126289.17
C93: L | E93: Actividades inmobiliarias | F93: 32556 | G93: 35921 | H93: 39056 | I93: 42236 | J93: 45858 | K93: 49355 | L93: 52966 | M93: 56928 | N93: 60922 | O93: 65194 | P93: 69825 | Q93: 75645 | R93: 80976 | S93: 86825 | T93: 92388 | U93: 95042 | V93: 98900 | W93: 104886 | X93: 114270 | Y93: 126289.17
D94: 089 | E94: Actividades inmobiliarias | F94: 32556 | G94: 35921 | H94: 39056 | I94: 42236 | J94: 45858 | K94: 49355 | L94: 52966 | M94: 56928 | N94: 60922 | O94: 65194 | P94: 69825 | Q94: 75645 | R94: 80976 | S94: 86825 | T94: 92388 | U94: 95042 | V94: 98900 | W94: 104886 | X94: 114270 | Y94: 126289.17
B95: M + N | E95: Actividades profesionales, científicas y técnicas; Actividades de servicios administrativos y de apoyo | F95: 16684 | G95: 19444 | H95: 23068 | I95: 26411 | J95: 29840 | K95: 33567 | L95: 38275 | M95: 43078 | N95: 48022 | O95: 55216 | P95: 57392 | Q95: 59643 | R95: 62898 | S95: 67597 | T95: 72458 | U95: 69363 | V95: 79121 | W95: 93635 | X95: 103660 | Y95: 111589.32
C96: M + N | E96: Actividades profesionales, científicas y técnicas; Actividades de servicios administrativos y de apoyo | F96: 16684 | G96: 19444 | H96: 23068 | I96: 26411 | J96: 29840 | K96: 33567 | L96: 38275 | M96: 43078 | N96: 48022 | O96: 55216 | P96: 57392 | Q96: 59643 | R96: 62898 | S96: 67597 | T96: 72458 | U96: 69363 | V96: 79121 | W96: 93635 | X96: 103660 | Y96: 111589.32
D97: 090 - 093 | E97: Actividades profesionales, científicas y técnicas | F97: 7525 | G97: 8819 | H97: 10533 | I97: 12140 | J97: 13806 | K97: 15627 | L97: 17921 | M97: 20300 | N97: 22764 | O97: 26337 | P97: 27057 | Q97: 27899 | R97: 28877 | S97: 31007 | T97: 33073 | U97: 31452 | V97: 35959 | W97: 42276 | X97: 46605 | Y97: 50661.73
D98: 094 - 097 | E98: Actividades de servicios administrativos y de apoyo | F98: 9159 | G98: 10625 | H98: 12535 | I98: 14271 | J98: 16034 | K98: 17940 | L98: 20354 | M98: 22778 | N98: 25258 | O98: 28879 | P98: 30335 | Q98: 31744 | R98: 34021 | S98: 36590 | T98: 39385 | U98: 37911 | V98: 43162 | W98: 51359 | X98: 57055 | Y98: 60927.59
B99: O + P + Q | E99: Administración pública y defensa; planes de seguridad social de afiliación obligatoria; Educación; Actividades de atención de la salud humana y de servicios sociales | F99: 43348 | G99: 47526 | H99: 52624 | I99: 57489 | J99: 63821 | K99: 69620 | L99: 75682 | M99: 84164 | N99: 93615 | O99: 102459 | P99: 112077 | Q99: 123511 | R99: 135235 | S99: 147217 | T99: 159762 | U99: 163472 | V99: 181115 | W99: 197334 | X99: 228088 | Y99: 257495.62
C100: O | E100: Administración pública y defensa; planes de seguridad social de afiliación obligatoria | F100: 17212 | G100: 18889 | H100: 21231 | I100: 23196 | J100: 26213 | K100: 28573 | L100: 30909 | M100: 33723 | N100: 38204 | O100: 41793 | P100: 45797 | Q100: 50974 | R100: 55384 | S100: 60592 | T100: 64910 | U100: 66288 | V100: 69863 | W100: 75388 | X100: 86261 | Y100: 96971.09
D101: 098, 099 | E101: Administración pública y defensa; planes de seguridad social de afiliación obligatoria | F101: 17212 | G101: 18889 | H101: 21231 | I101: 23196 | J101: 26213 | K101: 28573 | L101: 30909 | M101: 33723 | N101: 38204 | O101: 41793 | P101: 45797 | Q101: 50974 | R101: 55384 | S101: 60592 | T101: 64910 | U101: 66288 | V101: 69863 | W101: 75388 | X101: 86261 | Y101: 96971.09
C102: P | E102: Educación | F102: 14933 | G102: 16056 | H102: 17713 | I102: 19740 | J102: 21725 | K102: 23395 | L102: 25451 | M102: 28402 | N102: 31076 | O102: 33602 | P102: 36860 | Q102: 40731 | R102: 44053 | S102: 47297 | T102: 52245 | U102: 55538 | V102: 59459 | W102: 65052 | X102: 74287 | Y102: 84339.24
D103: 100 | E103: Educación de mercado | F103: 7500 | G103: 8179 | H103: 9129 | I103: 9735 | J103: 10886 | K103: 11677 | L103: 12829 | M103: 14146 | N103: 15640 | O103: 17116 | P103: 18575 | Q103: 20228 | R103: 22259 | S103: 23668 | T103: 25231 | U103: 24264 | V103: 25829 | W103: 29599 | X103: 33960 | Y103: 37520.74
D104: 101 | E104: Educación de no mercado | F104: 7433 | G104: 7877 | H104: 8584 | I104: 10005 | J104: 10839 | K104: 11718 | L104: 12622 | M104: 14256 | N104: 15436 | O104: 16486 | P104: 18285 | Q104: 20503 | R104: 21794 | S104: 23629 | T104: 27014 | U104: 31274 | V104: 33630 | W104: 35453 | X104: 40327 | Y104: 46818.51
C105: Q | E105: Actividades de atención de la salud humana y de servicios sociales | F105: 11203 | G105: 12581 | H105: 13680 | I105: 14553 | J105: 15883 | K105: 17652 | L105: 19322 | M105: 22039 | N105: 24335 | O105: 27064 | P105: 29420 | Q105: 31806 | R105: 35798 | S105: 39328 | T105: 42607 | U105: 41646 | V105: 51793 | W105: 56894 | X105: 67540 | Y105: 76185.29
D106: 102, 103 | E106: Actividades de atención de la salud humana y de servicios sociales | F106: 11203 | G106: 12581 | H106: 13680 | I106: 14553 | J106: 15883 | K106: 17652 | L106: 19322 | M106: 22039 | N106: 24335 | O106: 27064 | P106: 29420 | Q106: 31806 | R106: 35798 | S106: 39328 | T106: 42607 | U106: 41646 | V106: 51793 | W106: 56894 | X106: 67540 | Y106: 76185.29
...

Sheet Cuadro 2
A3: Producto Interno Bruto - PIB
A5: Series encadenadas de volumen con año de referencia 2015
A6: Miles de millones de pesos
A7: 2005 - 2024pr | Y7: Índice
A9: Clasificación Cuentas Nacionales | B9: Secciones CIIU Rev. 4 A.C. 12 agrupaciones | C9: Secciones y divisiones CIIU Rev. 4 A.C. 25 agrupaciones | D9: Divisiones CIIU Rev. 4 A.C. 61 agrupaciones | E9: Concepto | F9: 2005 | G9: 2006 | H9: 2007 | I9: 2008 | J9: 2009 | K9: 2010 | L9: 2011 | M9: 2012 | N9: 2013 | O9: 2014 | P9: 2015 | Q9: 2016 | R9: 2017 | S9: 2018 | T9: 2019 | U9: 2020 | V9: 2021 | W9: 2022 | X9: 2023p | Y9: 2024pr
A11: PIB enfoque de la producción
B13: A | E13: Agricultura, ganadería, caza, silvicultura y pesca | F13: 37909 | G13: 38717 | H13: 40239 | I13: 39915 | J13: 39822 | K13: 39943 | L13: 40706 | M13: 41725 | N13: 44835 | O13: 46140 | P13: 48124 | Q13: 49441 | R13: 52198 | S13: 53030 | T13: 54471 | U13: 55539 | V13: 57968 | W13: 57442 | X13: 58406 | Y13: 63061.23
C14: A | E14: Agricultura, ganadería, caza, silvicultura y pesca | F14: 37909 | G14: 38717 | H14: 40239 | I14: 39915 | J14: 39822 | K14: 39943 | L14: 40706 | M14: 41725 | N14: 44835 | O14: 46140 | P14: 48124 | Q14: 49441 | R14: 52198 | S14: 53030 | T14: 54471 | U14: 55539 | V14: 57968 | W14: 57442 | X14: 58406 | Y14: 63061.23
D15: 001 - 008, 013 | E15: Cultivos agrícolas transitorios; otros cultivos agrícolas permanentes; Propagación de plantas (actividades de viveros, excepto viveros forestales); actividades de apoyo a la agricultura y la ganadería, y posteriores a la cosecha, explotación mixta (agrícola y pecuaria) y caza ordinaria y mediante trampas y actividades de servicios conexas | F15: 21844 | G15: 21729 | H15: 22630 | I15: 22152 | J15: 23060 | K15: 22863 | L15: 23482 | M15: 24221 | N15: 25727 | O15: 26164 | P15: 27339 | Q15: 28339 | R15: 30612 | S15: 30933 | T15: 31344 | U15: 32005 | V15: 33477 | W15: 33829 | X15: 34677 | Y15: 37349.47
D16: 003 | E16: Cultivo permanente de café | F16: 3845 | G16: 4153 | H16: 4336 | I16: 3972 | J16: 3066 | K16: 3415 | L16: 3134 | M16: 3066 | N16: 4167 | O16: 4810 | P16: 5299 | Q16: 5489 | R16: 5470 | S16: 5393 | T16: 5981 | U16: 5327 | V16: 5140 | W16: 4232 | X16: 4403 | Y16: 5384.5
D17: 009 - 012 | E17: Ganadería | F17: 9857 | G17: 10271 | H17: 10633 | I17: 11033 | J17: 10996 | K17: 10902 | L17: 11348 | M17: 11652 | N17: 11930 | O17: 11959 | P17: 12265 | Q17: 12418 | R17: 12956 | S17: 13400 | T17: 13729 | U17: 14259 | V17: 15223 | W17: 15300 | X17: 15068 | Y17: 15920.56
D18: 014, 015 | E18: Silvicultura y extracción de madera | F18: 1332 | G18: 1351 | H18: 1366 | I18: 1367 | J18: 1394 | K18: 1423 | L18: 1494 | M18: 1593 | N18: 1652 | O18: 1759 | P18: 1796 | Q18: 1837 | R18: 1856 | S18: 1877 | T18: 1963 | U18: 2029 | V18: 2107 | W18: 2143 | X18: 2129 | Y18: 2086.45
D19: 016 | E19: Pesca y acuicultura | F19: 1252 | G19: 1346 | H19: 1422 | I19: 1455 | J19: 1380 | K19: 1354 | L19: 1359 | M19: 1405 | N19: 1424 | O19: 1448 | P19: 1425 | Q19: 1358 | R19: 1295 | S19: 1410 | T19: 1446 | U19: 1878 | V19: 2059 | W19: 2325 | X19: 2331 | Y19: 2261.38
B20: B | E20: Explotación de minas y canteras | F20: 27430 | G20: 28059 | H20: 28434 | I20: 31101 | J20: 34659 | K20: 38427 | L20: 43974 | M20: 46335 | N20: 48794 | O20: 48136 | P20: 47627 | Q20: 46253 | R20: 43592 | S20: 42868 | T20: 43693 | U20: 37056 | V20: 36980 | W20: 37518 | X20: 38496 | Y20: 36555
C21: B | E21: Explotación de minas y canteras | F21: 27430 | G21: 28059 | H21: 28434 | I21: 31101 | J21: 34659 | K21: 38427 | L21: 43974 | M21: 46335 | N21: 48794 | O21: 48136 | P21: 47627 | Q21: 46253 | R21: 43592 | S21: 42868 | T21: 43693 | U21: 37056 | V21: 36980 | W21: 37518 | X21: 38496 | Y21: 36555
D22: 017 | E22: Extracción de carbón de piedra y lignito | F22: 6106 | G22: 6772 | H22: 7240 | I22: 7606 | J22: 7578 | K22: 7721 | L22: 8857 | M22: 9199 | N22: 8829 | O22: 9099 | P22: 8833 | Q22: 10031 | R22: 9996 | S22: 9447 | T22: 9329 | U22: 6021 | V22: 6490 | W22: 6539 | X22: 6687 | Y22: 5820.33
D23: 018, 021 | E23: Extracción de petróleo crudo y gas natural y actividades de apoyo para la extracción de petróleo y de gas natural | F23: 16418 | G23: 16323 | H23: 16367 | I23: 18886 | J23: 21756 | K23: 25403 | L23: 29921 | M23: 31308 | N23: 33967 | O23: 33135 | P23: 32852 | Q23: 29705 | R23: 28532 | S23: 29011 | T23: 29826 | U23: 26499 | V23: 24776 | W23: 25259 | X23: 25946 | Y23: 25776.61
D24: 019 | E24: Extracción de minerales metalíferos | F24: 4157 | G24: 4077 | H24: 3834 | I24: 3574 | J24: 4174 | K24: 4203 | L24: 3733 | M24: 4432 | N24: 3876 | O24: 3820 | P24: 3592 | Q24: 4064 | R24: 2982 | S24: 2574 | T24: 2710 | U24: 3185 | V24: 3511 | W24: 3557 | X24: 3710 | Y24: 3412.09
D25: 020 | E25: Extracción de otras minas y canteras | F25: 1267 | G25: 1391 | H25: 1529 | I25: 1629 | J25: 1696 | K25: 1492 | L25: 1581 | M25: 1621 | N25: 1786 | O25: 1990 | P25: 2156 | Q25: 2232 | R25: 2175 | S25: 2144 | T25: 2235 | U25: 1504 | V25: 1661 | W25: 1634 | X25: 1619 | Y25: 1664.9
D26: 022 | E26: Actividades de apoyo para otras actividades de explotación de minas y canteras | F26: 143 | G26: 152 | H26: 155 | I26: 156 | J26: 164 | K26: 164 | L26: 172 | M26: 186 | N26: 177 | O26: 182 | P26: 194 | Q26: 221 | R26: 179 | S26: 181 | T26: 178 | U26: 148 | V26: 162 | W26: 163 | X26: 163 | Y26: 158.27
B27: C | E27: Industrias manufactureras | F27: 77252 | G27: 82885 | H27: 89320 | I27: 89639 | J27: 86354 | K27: 87980 | L27: 92896 | M27: 93667 | N27: 95081 | O27: 97829 | P27: 99789 | Q27: 103006 | R27: 101135 | S27: 102627 | T27: 103860 | U27: 94254 | V27: 107066 | W27: 115802 | X27: 112628 | Y27: 110281.94
C28: C01 | E28: Elaboración de productos alimenticios; elaboración de bebidas; elaboración de productos de tabaco | F28: 21322 | G28: 22235 | H28: 23431 | I28: 24041 | J28: 24387 | K28: 23932 | L28: 24803 | M28: 25068 | N28: 25935 | O28: 26660 | P28: 27219 | Q28: 27871 | R28: 27924 | S28: 28594 | T28: 29391 | U28: 28425 | V28: 30075 | W28: 32252 | X28: 31968 | Y28: 31721.05
D29: 023 - 025 | E29: Procesamiento y conservación de carne y productos cárnicos de bovinos, bufalinos, porcinos y otras carnes n.c.p.; procesamiento y conservación de carne y productos cárnicos de aves de corral y procesamiento y conservación de pescados, crustáceos y moluscos | F29: 4355 | G29: 4578 | H29: 4901 | I29: 5176 | J29: 5202 | K29: 5217 | L29: 5407 | M29: 5626 | N29: 5646 | O29: 5742 | P29: 5896 | Q29: 6033 | R29: 6013 | S29: 6313 | T29: 6650 | U29: 6752 | V29: 7094 | W29: 7491 | X29: 7660 | Y29: 7842.24
D30: 026 | E30: Elaboración de aceites y grasas de origen vegetal y animal | F30: 978 | G30: 987 | H30: 1038 | I30: 1059 | J30: 1129 | K30: 1173 | L30: 1237 | M30: 1250 | N30: 1314 | O30: 1392 | P30: 1506 | Q30: 1508 | R30: 1570 | S30: 1494 | T30: 1522 | U30: 1435 | V30: 1655 | W30: 1720 | X30: 1690 | Y30: 1569.08
D31: 027 | E31: Elaboración de productos lácteos | F31: 2609 | G31: 2659 | H31: 2726 | I31: 2880 | J31: 2855 | K31: 2838 | L31: 2947 | M31: 2981 | N31: 3139 | O31: 3177 | P31: 3217 | Q31: 3271 | R31: 3301 | S31: 3312 | T31: 3371 | U31: 3405 | V31: 3127 | W31: 3159 | X31: 3019 | Y31: 2914.95
D32: 028, 032, 035 | E32: Elaboración de productos de molinería, almidones y productos derivados del almidón; elaboración de productos de panadería; elaboración de macarrones, fideos, alcuzcuz, y productos farináceos similares y elaboración de alimentos preparados para animales | F32: 3401 | G32: 3504 | H32: 3762 | I32: 3883 | J32: 3817 | K32: 3908 | L32: 4030 | M32: 3966 | N32: 3918 | O32: 3825 | P32: 3922 | Q32: 4237 | R32: 4336 | S32: 4398 | T32: 4585 | U32: 4801 | V32: 4615 | W32: 4917 | X32: 4735 | Y32: 4521.64
D33: 029 | E33: Elaboración de productos de café | F33: 616 | G33: 638 | H33: 633 | I33: 609 | J33: 471 | K33: 486 | L33: 453 | M33: 418 | N33: 564 | O33: 631 | P33: 702 | Q33: 715 | R33: 736 | S33: 713 | T33: 793 | U33: 649 | V33: 640 | W33: 608 | X33: 606 | Y33: 693.47
D34: 030, 031 | E34: Elaboración de azúcar y elaboración de panela | F34: 2056 | G34: 2256 | H34: 2194 | I34: 2097 | J34: 2398 | K34: 2104 | L34: 2328 | M34: 2297 | N34: 2411 | O34: 2721 | P34: 2618 | Q34: 2381 | R34: 2424 | S34: 2465 | T34: 2439 | U34: 2448 | V34: 2489 | W34: 2546 | X34: 2439 | Y34: 2565.03
D35: 033 | E35: Elaboración de cacao, chocolate y productos de confitería | F35: 615 | G35: 619 | H35: 641 | I35: 691 | J35: 683 | K35: 658 | L35: 662 | M35: 670 | N35: 663 | O35: 704 | P35: 688 | Q35: 702 | R35: 723 | S35: 781 | T35: 828 | U35: 813 | V35: 915 | W35: 1032 | X35: 997 | Y35: 958.52
D36: 034 | E36: Procesamiento y conservación de frutas, legumbres, hortalizas y tubérculos; elaboración de otros productos alimenticios (platos preparados y conservados mediante enlatado o congelado, elaboración de sopas y caldos en estado sólidos, polvo o instantáneas entre otros) | F36: 1597 | G36: 1719 | H36: 1948 | I36: 1991 | J36: 2022 | K36: 1983 | L36: 2016 | M36: 2030 | N36: 2143 | O36: 2187 | P36: 2276 | Q36: 2329 | R36: 2308 | S36: 2365 | T36: 2361 | U36: 2411 | V36: 2506 | W36: 2769 | X36: 2620 | Y36: 2542.27
D37: 036 | E37: Elaboración de bebidas (incluido el hielo) y elaboración de productos de tabaco | F37: 4977 | G37: 5204 | H37: 5610 | I37: 5705 | J37: 5833 | K37: 5585 | L37: 5657 | M37: 5804 | N37: 6110 | O37: 6274 | P37: 6394 | Q37: 6695 | R37: 6495 | S37: 6746 | T37: 6862 | U37: 5718 | V37: 7078 | W37: 8140 | X37: 8367 | Y37: 8308.44
C38: C02 | E38: Fabricación de productos textiles; confección de prendas de vestir; curtido y recurtido de cueros; fabricación de calzado; fabricación de artículos de viaje, maletas, bolsos de mano y artículos similares, y fabricación de artículos de talabartería y guarnicionería; adobo y teñido de pieles | F38: 8833 | G38: 9638 | H38: 10852 | I38: 10760 | J38: 9324 | K38: 9642 | L38: 10422 | M38: 10355 | N38: 10128 | O38: 10303 | P38: 10343 | Q38: 10815 | R38: 10510 | S38: 10397 | T38: 10473 | U38: 8241 | V38: 11683 | W38: 13106 | X38: 11464 | Y38: 11045.48
D39: 037, 038 | E39: Preparación, hilatura, tejeduría y acabado de productos textiles; fabricación de otros productos textiles, Confección de prendas de vestir | F39: 7341 | G39: 8075 | H39: 9064 | I39: 8826 | J39: 7734 | K39: 7967 | L39: 8555 | M39: 8552 | N39: 8428 | O39: 8552 | P39: 8584 | Q39: 9004 | R39: 8693 | S39: 8729 | T39: 8892 | U39: 7272 | V39: 10245 | W39: 11560 | X39: 10064 | Y39: 9721.5
D40: 039 | E40: Curtido y recurtido de cueros; fabricación de calzado; fabricación de artículos de viaje, maletas, bolsos de mano y artículos similares, y fabricación de artículos de talabartería y guarnicionería; adobo y teñido de pieles | F40: 1496 | G40: 1569 | H40: 1793 | I40: 1927 | J40: 1593 | K40: 1676 | L40: 1866 | M40: 1803 | N40: 1701 | O40: 1751 | P40: 1759 | Q40: 1811 | R40: 1817 | S40: 1653 | T40: 1554 | U40: 902 | V40: 1353 | W40: 1436 | X40: 1313 | Y40: 1235.06
C41: C03 | E41: Transformación de la madera y fabricación de productos de madera y de corcho, excepto muebles; fabricación de artículos de cestería y espartería; fabricación de papel, cartón y productos de papel y de cartón; actividades de impresión; producción de copias a partir de grabaciones originales | F41: 4590 | G41: 4917 | H41: 5249 | I41: 5345 | J41: 5274 | K41: 5406 | L41: 5541 | M41: 5671 | N41: 5660 | O41: 5782 | P41: 6057 | Q41: 6414 | R41: 6404 | S41: 6431 | T41: 6389 | U41: 5921 | V41: 6192 | W41: 6689 | X41: 6656 | Y41: 6641.05
D42: 040 | E42: Transformación de la madera y fabricación de productos de madera y de corcho, excepto muebles; fabricación de artículos de cestería y espartería | F42: 1002 | G42: 1093 | H42: 1210 | I42: 1162 | J42: 1056 | K42: 1052 | L42: 1027 | M42: 1009 | N42: 1032 | O42: 1059 | P42: 1137 | Q42: 1161 | R42: 1121 | S42: 1028 | T42: 965 | U42: 884 | V42: 921 | W42: 1086 | X42: 955 | Y42: 888.78
D43: 041 | E43: Fabricación de papel, cartón y productos de papel y de cartón | F43: 2181 | G43: 2355 | H43: 2481 | I43: 2581 | J43: 2589 | K43: 2769 | L43: 2881 | M43: 2989 | N43: 2995 | O43: 3131 | P43: 3219 | Q43: 3468 | R43: 3567 | S43: 3707 | T43: 3769 | U43: 3525 | V43: 3621 | W43: 3797 | X43: 3888 | Y43: 3917.22
D44: 042 | E44: Actividades de impresión; producción de copias a partir de grabaciones originales (Copia a partir de un original en CD, DVD, Bluray) | F44: 1442 | G44: 1500 | H44: 1608 | I44: 1632 | J44: 1651 | K44: 1578 | L44: 1627 | M44: 1673 | N44: 1633 | O44: 1603 | P44: 1701 | Q44: 1785 | R44: 1722 | S44: 1706 | T44: 1666 | U44: 1519 | V44: 1669 | W44: 1849 | X44: 1813 | Y44: 1827.33
C45: C04 | E45: Coquización, fabricación de productos de la refinación del petróleo y actividad de mezcla de combustibles; fabricación de sustancias y productos químicos; fabricación de productos farmacéuticos, sustancias químicas medicinales y productos botánicos de uso farmacéutico; fabricación de productos de caucho y de plástico; fabricación de otros productos minerales no metálicos | F45: 26681 | G45: 28964 | H45: 30971 | I45: 31407 | J45: 30481 | K45: 30822 | L45: 32688 | M45: 32768 | N45: 33774 | O45: 34786 | P45: 35555 | Q45: 37081 | R45: 37118 | S45: 37535 | T45: 37685 | U45: 33901 | V45: 38222 | W45: 40657 | X45: 40114 | Y45: 38706.5
D46: 043, 044 | E46: Coquización, fabricación de productos de la refinación del petróleo y actividades de mezcla de combustibles | F46: 7974 | G46: 8211 | H46: 8477 | I46: 8483 | J46: 8266 | K46: 8555 | L46: 8677 | M46: 8332 | N46: 8860 | O46: 8147 | P46: 7761 | Q46: 9223 | R46: 9836 | S46: 10282 | T46: 10214 | U46: 9036 | V46: 10625 | W46: 11170 | X46: 11961 | Y46: 11540.04
D47: 045 - 047 | E47: Fabricación de sustancias químicas básicas, abonos y compuestos inorgánicos nitrogenados, plásticos y caucho sintético en formas primarias; fabricación de otros productos químicos; fabricación de fibras sintéticas y artificiales; fabricación de productos farmacéuticos, sustancias químicas medicinales y productos botánicos de uso farmacéutico | F47: 8743 | G47: 9448 | H47: 10100 | I47: 10440 | J47: 10086 | K47: 10240 | L47: 10686 | M47: 10818 | N47: 11155 | O47: 11255 | P47: 11814 | Q47: 12062 | R47: 12032 | S47: 12245 | T47: 12514 | U47: 12103 | V47: 13567 | W47: 14531 | X47: 13897 | Y47: 13673.26
D48: 048 | E48: Fabricación de productos de caucho y de plástico | F48: 2140 | G48: 2247 | H48: 2416 | I48: 2422 | J48: 2408 | K48: 2476 | L48: 2640 | M48: 2616 | N48: 2626 | O48: 2660 | P48: 2791 | Q48: 2866 | R48: 2831 | S48: 2942 | T48: 3048 | U48: 2954 | V48: 3051 | W48: 3397 | X48: 3120 | Y48: 3107.21
D49: 049 | E49: Fabricación de otros productos minerales no metálicos | F49: 8161 | G49: 9320 | H49: 10159 | I49: 10213 | J49: 9847 | K49: 9722 | L49: 10816 | M49: 11112 | N49: 11280 | O49: 12743 | P49: 13189 | Q49: 12930 | R49: 12485 | S49: 12078 | T49: 11910 | U49: 9702 | V49: 10853 | W49: 11435 | X49: 10770 | Y49: 9974.04
C50: C05 | E50: Fabricación de productos metalúrgicos básicos; fabricación de productos elaborados de metal, excepto maquinaria y equipo; fabricación de aparatos y equipo eléctrico; fabricación de productos informáticos, electrónicos y ópticos; fabricación de maquinaria y equipo n.c.p.; fabricación de vehículos automotores, remolques y semirremolques; fabricación de otros tipos de equipo de transporte; instalación, mantenimiento y reparación especializado de maquinaria y equipo | F50: 11299 | G50: 12393 | H50: 13734 | I50: 12946 | J50: 12020 | K50: 13136 | L50: 14287 | M50: 14502 | N50: 14298 | O50: 14852 | P50: 15004 | Q50: 15267 | R50: 13725 | S50: 14032 | T50: 14297 | U50: 12818 | V50: 15196 | W50: 17042 | X50: 16232 | Y50: 16137.1
D51: 050, 051 | E51: Fabricación de productos metalúrgicos básicos; fabricación de productos elaborados de metal, excepto maquinaria y equipo | F51: 4503 | G51: 4833 | H51: 5048 | I51: 5127 | J51: 5144 | K51: 5320 | L51: 5617 | M51: 5784 | N51: 5573 | O51: 5841 | P51: 5946 | Q51: 6172 | R51: 5707 | S51: 5627 | T51: 5671 | U51: 5517 | V51: 6687 | W51: 7293 | X51: 6986 | Y51: 6851.62
D52: 052 | E52: Fabricación de aparatos y equipo eléctrico; fabricación de productos informáticos, electrónicos y ópticos | F52: 1440 | G52: 1589 | H52: 1681 | I52: 1581 | J52: 1489 | K52: 1653 | L52: 1814 | M52: 1718 | N52: 1834 | O52: 1857 | P52: 1920 | Q52: 2043 | R52: 1940 | S52: 2041 | T52: 2114 | U52: 2007 | V52: 2318 | W52: 2618 | X52: 2643 | Y52: 2790.62
D53: 053, 057 | E53: Fabricación de maquinaria y equipo n.c.p.; instalación, mantenimiento y reparación especializado de maquinaria y equipo | F53: 3705 | G53: 3954 | H53: 4356 | I53: 4396 | J53: 3869 | K53: 4118 | L53: 4310 | M53: 4312 | N53: 4450 | O53: 4547 | P53: 4635 | Q53: 4628 | R53: 3793 | S53: 3902 | T53: 3994 | U53: 3564 | V53: 3795 | W53: 4249 | X53: 4502 | Y53: 4613.96
D54: 054 | E54: Fabricación de vehículos automotores, remolques y semirremolques; fabricación de otros tipos de equipo de transporte | F54: 1675 | G54: 1958 | H54: 2405 | I54: 1850 | J54: 1619 | K54: 2082 | L54: 2522 | M54: 2680 | N54: 2431 | O54: 2597 | P54: 2503 | Q54: 2424 | R54: 2276 | S54: 2474 | T54: 2544 | U54: 1637 | V54: 2171 | W54: 2718 | X54: 1998 | Y54: 1857.44
C55: C06 | E55: Fabricación de muebles, colchones y somieres; otras industrias manufactureras | F55: 4398 | G55: 4699 | H55: 4981 | I55: 5119 | J55: 4779 | K55: 4987 | L55: 5134 | M55: 5259 | N55: 5279 | O55: 5435 | P55: 5611 | Q55: 5558 | R55: 5429 | S55: 5586 | T55: 5557 | U55: 4916 | V55: 5857 | W55: 6403 | X55: 6145 | Y55: 6028.65
D56: 055 | E56: Fabricación de muebles, colchones y somieres | F56: 1654 | G56: 1721 | H56: 1851 | I56: 1889 | J56: 1851 | K56: 1912 | L56: 2068 | M56: 2114 | N56: 2175 | O56: 2204 | P56: 2306 | Q56: 2358 | R56: 2348 | S56: 2353 | T56: 2399 | U56: 2003 | V56: 2501 | W56: 2511 | X56: 2297 | Y56: 2142.59
D57: 056 | E57: Otras industrias manufactureras | F57: 2768 | G57: 3012 | H57: 3161 | I57: 3266 | J57: 2941 | K57: 3092 | L57: 3069 | M57: 3148 | N57: 3103 | O57: 3233 | P57: 3305 | Q57: 3200 | R57: 3082 | S57: 3226 | T57: 3158 | U57: 2897 | V57: 3350 | W57: 3869 | X57: 3820 | Y57: 3860.15
B58: D + E | E58: Suministro de electricidad, gas, vapor y aire acondicionado; Distribución de agua; evacuación y tratamiento de aguas residuales, gestión de desechos y actividades de saneamiento ambiental | F58: 18685 | G58: 19679 | H58: 20511 | I58: 20619 | J58: 21113 | K58: 21935 | L58: 22608 | M58: 23094 | N58: 23950 | O58: 24773 | P58: 24599 | Q58: 24597 | R58: 25307 | S58: 25952 | T58: 26606 | U58: 25587 | V58: 27079 | W58: 28327 | X58: 28958 | Y58: 29494.53
C59: D | E59: Suministro de electricidad, gas, vapor y aire acondicionado | F59: 12577 | G59: 13131 | H59: 13760 | I59: 13742 | J59: 14204 | K59: 14888 | L59: 15386 | M59: 15748 | N59: 16384 | O59: 17031 | P59: 16842 | Q59: 16990 | R59: 17519 | S59: 18004 | T59: 18549 | U59: 18287 | V59: 19492 | W59: 20362 | X59: 21011 | Y59: 21551.54
D60: 058 - 060 | E60: Generación de energía eléctrica; transmisión de energía eléctrica y distribución y comercialización de energía eléctrica | F60: 10917 | G60: 11384 | H60: 11811 | I60: 11988 | J60: 12152 | K60: 12705 | L60: 13046 | M60: 13301 | N60: 13758 | O60: 14207 | P60: 14017 | Q60: 14140 | R60: 14635 | S60: 15065 | T60: 15513 | U60: 15442 | V60: 16295 | W60: 16930 | X60: 17700 | Y60: 18209.07
D61: 061 | E61: Producción de gas; distribución de combustibles gaseosos por tuberías; suministro de vapor y aire acondicionado | F61: 1686 | G61: 1773 | H61: 1949 | I61: 1807 | J61: 2013 | K61: 2145 | L61: 2309 | M61: 2422 | N61: 2608 | O61: 2816 | P61: 2825 | Q61: 2850 | R61: 2888 | S61: 2946 | T61: 3042 | U61: 2866 | V61: 3194 | W61: 3420 | X61: 3300 | Y61: 3326.8
C62: E | E62: Distribución de agua; evacuación y tratamiento de aguas residuales, gestión de desechos y actividades de saneamiento ambiental | F62: 6089 | G62: 6501 | H62: 6717 | I62: 6826 | J62: 6873 | K62: 7030 | L62: 7210 | M62: 7338 | N62: 7563 | O62: 7744 | P62: 7757 | Q62: 7607 | R62: 7784 | S62: 7944 | T62: 8053 | U62: 7299 | V62: 7583 | W62: 7959 | X62: 7936 | Y62: 7907.37
D63: 062 | E63: Captación, tratamiento y distribución de agua | F63: 1958 | G63: 1985 | H63: 2012 | I63: 2031 | J63: 2057 | K63: 2073 | L63: 2128 | M63: 2218 | N63: 2311 | O63: 2366 | P63: 2376 | Q63: 2349 | R63: 2370 | S63: 2430 | T63: 2523 | U63: 2358 | V63: 2324 | W63: 2368 | X63: 2421 | Y63: 2394.86
D64: 063, 064, 066 | E64: Evacuación y tratamiento de aguas residuales; recolección, tratamiento y disposición de desechos y actividades de saneamiento ambiental y otros servicios de gestión de desechos | F64: 3148 | G64: 3506 | H64: 3657 | I64: 3731 | J64: 3737 | K64: 3828 | L64: 3923 | M64: 3936 | N64: 4031 | O64: 4116 | P64: 4068 | Q64: 3969 | R64: 3992 | S64: 4057 | T64: 4151 | U64: 3902 | V64: 3791 | W64: 3987 | X64: 4228 | Y64: 4181.87
D65: 065 | E65: Recuperación de materiales (reciclaje) | F65: 973 | G65: 1015 | H65: 1053 | I65: 1069 | J65: 1082 | K65: 1131 | L65: 1162 | M65: 1185 | N65: 1221 | O65: 1261 | P65: 1313 | Q65: 1289 | R65: 1426 | S65: 1462 | T65: 1366 | U65: 977 | V65: 1371 | W65: 1483 | X65: 1257 | Y65: 1294.22
B66: F | E66: Construcción | F66: 29808 | G66: 33427 | H66: 35747 | I66: 39289 | J66: 40316 | K66: 40048 | L66: 42536 | M66: 45051 | N66: 50131 | O66: 54602 | P66: 58042 | Q66: 60125 | R66: 58907 | S66: 58156 | T66: 55893 | U66: 39359 | V66: 41039 | W66: 43765 | X66: 42389 | Y66: 43194.86
C67: F01 | E67: Construcción de edificaciones residenciales y no residenciales | F67: 17573 | G67: 19701 | H67: 20410 | I67: 22928 | J67: 22324 | K67: 22035 | L67: 22711 | M67: 24045 | N67: 26444 | O67: 28294 | P67: 30111 | Q67: 31906 | R67: 30260 | S67: 30166 | T67: 26055 | U67: 18202 | V67: 20121 | W67: 22528 | X67: 22599 | Y67: 22042.91
D68: 067 | E68: Construcción de edificaciones residenciales y no residenciales | F68: 17573 | G68: 19701 | H68: 20410 | I68: 22928 | J68: 22324 | K68: 22035 | L68: 22711 | M68: 24045 | N68: 26444 | O68: 28294 | P68: 30111 | Q68: 31906 | R68: 30260 | S68: 30166 | T68: 26055 | U68: 18202 | V68: 20121 | W68: 22528 | X68: 22599 | Y68: 22042.91
C69: F02 | E69: Construcción de carreteras y vías de ferrocarril, de proyectos de servicio público y de otras obras de ingeniería civil | F69: 6311 | G69: 7081 | H69: 8199 | I69: 8547 | J69: 9742 | K69: 9751 | L69: 11003 | M69: 11662 | N69: 13177 | O69: 14914 | P69: 15906 | Q69: 15492 | R69: 16505 | S69: 16106 | T69: 18250 | U69: 13290 | V69: 12318 | W69: 11793 | X69: 10312 | Y69: 11515.75
D70: 068 | E70: Construcción de carreteras y vías de ferrocarril, de proyectos de servicio público y de otras obras de ingeniería civil | F70: 6311 | G70: 7081 | H70: 8199 | I70: 8547 | J70: 9742 | K70: 9751 | L70: 11003 | M70: 11662 | N70: 13177 | O70: 14914 | P70: 15906 | Q70: 15492 | R70: 16505 | S70: 16106 | T70: 18250 | U70: 13290 | V70: 12318 | W70: 11793 | X70: 10312 | Y70: 11515.75
C71: F03 | E71: Actividades especializadas para la construcción de edificaciones y obras de ingeniería civil (Alquiler de maquinaría y equipo de construcción con operadores) | F71: 6691 | G71: 7503 | H71: 7622 | I71: 8635 | J71: 8565 | K71: 8542 | L71: 8889 | M71: 9413 | N71: 10552 | O71: 11395 | P71: 12025 | Q71: 12727 | R71: 12221 | S71: 11979 | T71: 11671 | U71: 7978 | V71: 8642 | W71: 9478 | X71: 9523 | Y71: 9666.35
D72: 069 | E72: Actividades especializadas para la construcción de edificaciones y obras de ingeniería civil (Alquiler de maquinaría y equipo de construcción con operadores) | F72: 6691 | G72: 7503 | H72: 7622 | I72: 8635 | J72: 8565 | K72: 8542 | L72: 8889 | M72: 9413 | N72: 10552 | O72: 11395 | P72: 12025 | Q72: 12727 | R72: 12221 | S72: 11979 | T72: 11671 | U72: 7978 | V72: 8642 | W72: 9478 | X72: 9523 | Y72: 9666.35
B73: G + H + I | E73: Comercio al por mayor y al por menor; reparación de vehículos automotores y motocicletas; Transporte y almacenamiento; Alojamiento y servicios de comida | F73: 85427 | G73: 91926 | H73: 99343 | I73: 102346 | J73: 102185 | K73: 107647 | L73: 115063 | M73: 119453 | N73: 125149 | O73: 131063 | P73: 135429 | Q73: 139066 | R73: 141652 | S73: 145438 | T73: 150890 | U73: 130235 | V73: 156815 | W73: 175451 | X73: 169078 | Y73: 171424.43
C74: G | E74: Comercio al por mayor y al por menor; reparación de vehículos automotores y motocicletas | F74: 40676 | G74: 43932 | H74: 47673 | I74: 49047 | J74: 48605 | K74: 51171 | L74: 55266 | M74: 57437 | N74: 60130 | O74: 63124 | P74: 64866 | Q74: 67212 | R74: 68291 | S74: 70201 | T74: 73036 | U74: 70334 | V74: 81200 | W74: 86702 | X74: 82358 | Y74: 84934.36
D75: 070 | E75: Comercio al por mayor y en comisión o por contrata; comercio al por menor (incluso el comercio al por menor de combustibles); comercio de vehículos automotores y motocicletas, sus partes, piezas y accesorios | F75: 37007 | G75: 40046 | H75: 43574 | I75: 44861 | J75: 44304 | K75: 46676 | L75: 50641 | M75: 52609 | N75: 55024 | O75: 57696 | P75: 59399 | Q75: 61637 | R75: 62619 | S75: 64470 | T75: 67126 | U75: 65269 | V75: 75348 | W75: 80232 | X75: 75933 | Y75: 78496.26
D76: 071 | E76: Mantenimiento y reparación de vehículos automotores y motocicletas | F76: 3684 | G76: 3888 | H76: 4081 | I76: 4163 | J76: 4298 | K76: 4490 | L76: 4626 | M76: 4829 | N76: 5103 | O76: 5420 | P76: 5467 | Q76: 5575 | R76: 5673 | S76: 5730 | T76: 5910 | U76: 5041 | V76: 5824 | W76: 6463 | X76: 6470 | Y76: 6447.13
C77: H | E77: Transporte y almacenamiento | F77: 26666 | G77: 28455 | H77: 30515 | I77: 31322 | J77: 31075 | K77: 32835 | L77: 35146 | M77: 36429 | N77: 37733 | O77: 39278 | P77: 40703 | Q77: 40789 | R77: 41621 | S77: 42647 | T77: 44127 | U77: 34287 | V77: 40654 | W77: 48072 | X77: 48057 | Y77: 49073.07
D78: 072, 074 | E78: Transporte terrestre y transporte por tuberías | F78: 20186 | G78: 21060 | H78: 22665 | I78: 23112 | J78: 23028 | K78: 24131 | L78: 25187 | M78: 25846 | N78: 26271 | O78: 27166 | P78: 27868 | Q78: 27602 | R78: 27862 | S78: 28300 | T78: 28988 | U78: 23680 | V78: 26795 | W78: 30626 | X78: 31106 | Y78: 31613.76
D79: 073 | E79: Transporte acuático | F79: 209 | G79: 212 | H79: 229 | I79: 247 | J79: 225 | K79: 231 | L79: 234 | M79: 230 | N79: 227 | O79: 232 | P79: 231 | Q79: 235 | R79: 241 | S79: 243 | T79: 248 | U79: 229 | V79: 233 | W79: 252 | X79: 257 | Y79: 216.58
D80: 075 | E80: Transporte aéreo | F80: 2076 | G80: 2410 | H80: 2445 | I80: 2451 | J80: 2554 | K80: 2884 | L80: 3332 | M80: 3519 | N80: 3899 | O80: 4169 | P80: 4647 | Q80: 5016 | R80: 5309 | S80: 5659 | T80: 5981 | U80: 2613 | V80: 4133 | W80: 6856 | X80: 7078 | Y80: 7333.26
D81: 076 | E81: Almacenamiento y actividades complementarias al transporte | F81: 3929 | G81: 4358 | H81: 4661 | I81: 4943 | J81: 4679 | K81: 4917 | L81: 5663 | M81: 6055 | N81: 6466 | O81: 6793 | P81: 7055 | Q81: 7065 | R81: 7380 | S81: 7645 | T81: 8091 | U81: 6335 | V81: 8147 | W81: 9639 | X81: 9055 | Y81: 9352.41
D82: 077 | E82: Actividades de correo y de servicios de mensajería | F82: 461 | G82: 547 | H82: 644 | I82: 697 | J82: 691 | K82: 741 | L82: 786 | M82: 822 | N82: 864 | O82: 910 | P82: 902 | Q82: 871 | R82: 867 | S82: 904 | T82: 964 | U82: 990 | V82: 1119 | W82: 1186 | X82: 1101 | Y82: 1150.38
C83: I | E83: Alojamiento y servicios de comida | F83: 18155 | G83: 19580 | H83: 21157 | I83: 22018 | J83: 22655 | K83: 23796 | L83: 24756 | M83: 25686 | N83: 27318 | O83: 28679 | P83: 29860 | Q83: 31065 | R83: 31746 | S83: 32589 | T83: 33712 | U83: 24749 | V83: 34499 | W83: 41050 | X83: 39307 | Y83: 37811.25
D84: 078 - 080 | E84: Alojamiento y servicios de comida | F84: 18155 | G84: 19580 | H84: 21157 | I84: 22018 | J84: 22655 | K84: 23796 | L84: 24756 | M84: 25686 | N84: 27318 | O84: 28679 | P84: 29860 | Q84: 31065 | R84: 31746 | S84: 32589 | T84: 33712 | U84: 24749 | V84: 34499 | W84: 41050 | X84: 39307 | Y84: 37811.25
B85: J | E85: Información y comunicaciones | F85: 12730 | G85: 14629 | H85: 16761 | I85: 17120 | J85: 15669 | K85: 18256 | L85: 20153 | M85: 20415 | N85: 22218 | O85: 23654 | P85: 23961 | Q85: 23804 | R85: 23758 | S85: 24595 | T85: 24821 | U85: 24133 | V85: 27210 | W85: 30564 | X85: 31102 | Y85: 30863.2
C86: J | E86: Información y comunicaciones | F86: 12730 | G86: 14629 | H86: 16761 | I86: 17120 | J86: 15669 | K86: 18256 | L86: 20153 | M86: 20415 | N86: 22218 | O86: 23654 | P86: 23961 | Q86: 23804 | R86: 23758 | S86: 24595 | T86: 24821 | U86: 24133 | V86: 27210 | W86: 30564 | X86: 31102 | Y86: 30863.2
D87: 081 - 084 | E87: Información y comunicaciones | F87: 12730 | G87: 14629 | H87: 16761 | I87: 17120 | J87: 15669 | K87: 18256 | L87: 20153 | M87: 20415 | N87: 22218 | O87: 23654 | P87: 23961 | Q87: 23804 | R87: 23758 | S87: 24595 | T87: 24821 | U87: 24133 | V87: 27210 | W87: 30564 | X87: 31102 | Y87: 30863.2
B88: K | E88: Actividades financieras y de seguros | F88: 15424 | G88: 16440 | H88: 18702 | I88: 20598 | J88: 21315 | K88: 22312 | L88: 24754 | M88: 26626 | N88: 29160 | O88: 32139 | P88: 34696 | Q88: 35726 | R88: 37651 | S88: 39057 | T88: 41505 | U88: 42433 | V88: 44003 | W88: 46940 | X88: 51134 | Y88: 51334.96
C89: K | E89: Actividades financieras y de seguros | F89: 15424 | G89: 16440 | H89: 18702 | I89: 20598 | J89: 21315 | K89: 22312 | L89: 24754 | M89: 26626 | N89: 29160 | O89: 32139 | P89: 34696 | Q89: 35726 | R89: 37651 | S89: 39057 | T89: 41505 | U89: 42433 | V89: 44003 | W89: 46940 | X89: 51134 | Y89: 51334.96
D90: 085 - 088 | E90: Actividades financieras y de seguros | F90: 15424 | G90: 16440 | H90: 18702 | I90: 20598 | J90: 21315 | K90: 22312 | L90: 24754 | M90: 26626 | N90: 29160 | O90: 32139 | P90: 34696 | Q90: 35726 | R90: 37651 | S90: 39057 | T90: 41505 | U90: 42433 | V90: 44003 | W90: 46940 | X90: 51134 | Y90: 51334.96
B91: L | E91: Actividades inmobiliarias | F91: 50233 | G91: 52265 | H91: 54225 | I91: 55731 | J91: 57866 | K91: 59932 | L91: 61628 | M91: 63579 | N91: 65625 | O91: 67664 | P91: 69825 | Q91: 72289 | R91: 74495 | S91: 77449 | T91: 79964 | U91: 81118 | V91: 83143 | W91: 84843 | X91: 86490 | Y91: 88148.17
C92: L | E92: Actividades inmobiliarias | F92: 50233 | G92: 52265 | H92: 54225 | I92: 55731 | J92: 57866 | K92: 59932 | L92: 61628 | M92: 63579 | N92: 65625 | O92: 67664 | P92: 69825 | Q92: 72289 | R92: 74495 | S92: 77449 | T92: 79964 | U92: 81118 | V92: 83143 | W92: 84843 | X92: 86490 | Y92: 88148.17
D93: 089 | E93: Actividades inmobiliarias | F93: 50233 | G93: 52265 | H93: 54225 | I93: 55731 | J93: 57866 | K93: 59932 | L93: 61628 | M93: 63579 | N93: 65625 | O93: 67664 | P93: 69825 | Q93: 72289 | R93: 74495 | S93: 77449 | T93: 79964 | U93: 81118 | V93: 83143 | W93: 84843 | X93: 86490 | Y93: 88148.17
B94: M + N | E94: Actividades profesionales, científicas y técnicas; Actividades de servicios administrativos y de apoyo | F94: 36057 | G94: 38592 | H94: 41246 | I94: 42800 | J94: 43998 | K94: 45354 | L94: 48568 | M94: 50907 | N94: 53593 | O94: 57500 | P94: 57392 | Q94: 55995 | R94: 56810 | S94: 59066 | T94: 61102 | U94: 57564 | V94: 63167 | W94: 68132 | X94: 69464 | Y94: 69425.57
C95: M + N | E95: Actividades profesionales, científicas y técnicas; Actividades de servicios administrativos y de apoyo | F95: 36057 | G95: 38592 | H95: 41246 | I95: 42800 | J95: 43998 | K95: 45354 | L95: 48568 | M95: 50907 | N95: 53593 | O95: 57500 | P95: 57392 | Q95: 55995 | R95: 56810 | S95: 59066 | T95: 61102 | U95: 57564 | V95: 63167 | W95: 68132 | X95: 69464 | Y95: 69425.57
D96: 090 - 093 | E96: Actividades profesionales, científicas y técnicas | F96: 17311 | G96: 18519 | H96: 19787 | I96: 20529 | J96: 21116 | K96: 21757 | L96: 23283 | M96: 24399 | N96: 25690 | O96: 27555 | P96: 27057 | Q96: 26369 | R96: 26193 | S96: 27282 | T96: 28160 | U96: 26277 | V96: 28986 | W96: 30867 | X96: 31397 | Y96: 31620.94
D97: 094 - 097 | E97: Actividades de servicios administrativos y de apoyo | F97: 18749 | G97: 20076 | H97: 21461 | I97: 22273 | J97: 22885 | K97: 23600 | L97: 25288 | M97: 26511 | N97: 27907 | O97: 29949 | P97: 30335 | Q97: 29626 | R97: 30610 | S97: 31777 | T97: 32934 | U97: 31276 | V97: 34172 | W97: 37248 | X97: 38049 | Y97: 37789.07
B98: O + P + Q | E98: Administración pública y defensa; planes de seguridad social de afiliación obligatoria; Educación; Actividades de atención de la salud humana y de servicios sociales | F98: 71182 | G98: 74469 | H98: 77514 | I98: 79167 | J98: 81581 | K98: 85362 | L98: 90265 | M98: 95283 | N98: 100531 | O98: 106408 | P98: 112077 | Q98: 116198 | R98: 120222 | S98: 125916 | T98: 132333 | U98: 132742 | V98: 143974 | W98: 145589 | X98: 152886 | Y98: 157880
C99: O | E99: Administración pública y defensa; planes de seguridad social de afiliación obligatoria | F99: 25183 | G99: 26561 | H99: 27777 | I99: 28152 | J99: 29086 | K99: 31284 | L99: 34831 | M99: 37543 | N99: 39212 | O99: 43522 | P99: 45797 | Q99: 47413 | R99: 49286 | S99: 52157 | T99: 54352 | U99: 54180 | V99: 56352 | W99: 56962 | X99: 59066 | Y99: 60435.28
D100: 098, 099 | E100: Administración pública y defensa; planes de seguridad social de afiliación obligatoria | F100: 25183 | G100: 26561 | H100: 27777 | I100: 28152 | J100: 29086 | K100: 31284 | L100: 34831 | M100: 37543 | N100: 39212 | O100: 43522 | P100: 45797 | Q100: 47413 | R100: 49286 | S100: 52157 | T100: 54352 | U100: 54180 | V100: 56352 | W100: 56962 | X100: 59066 | Y100: 60435.28
C101: P | E101: Educación | F101: 26883 | G101: 27466 | H101: 28751 | I101: 29668 | J101: 30428 | K101: 31079 | L101: 31864 | M101: 33081 | N101: 34420 | O101: 35131 | P101: 36860 | Q101: 38468 | R101: 39046 | S101: 40259 | T101: 42231 | U101: 44108 | V101: 46569 | W101: 47457 | X101: 48873 | Y101: 50027.99
D102: 100 | E102: Educación de mercado | F102: 14084 | G102: 14482 | H102: 15040 | I102: 15197 | J102: 15465 | K102: 15573 | L102: 16056 | M102: 16568 | N102: 17287 | O102: 17925 | P102: 18575 | Q102: 19120 | R102: 19421 | S102: 19733 | T102: 20157 | U102: 19419 | V102: 20074 | W102: 21243 | X102: 21955 | Y102: 21979.23
D103: 101 | E103: Educación de no mercado | F103: 12820 | G103: 13013 | H103: 13733 | I103: 14485 | J103: 14969 | K103: 15506 | L103: 15809 | M103: 16514 | N103: 17135 | O103: 17207 | P103: 18285 | Q103: 19348 | R103: 19625 | S103: 20535 | T103: 22107 | U103: 24763 | V103: 26568 | W103: 26276 | X103: 26979 | Y103: 28128.42
C104: Q | E104: Actividades de atención de la salud humana y de servicios sociales | F104: 19832 | G104: 21135 | H104: 21684 | I104: 22112 | J104: 22837 | K104: 23573 | L104: 23797 | M104: 24817 | N104: 27055 | O104: 27758 | P104: 29420 | Q104: 30317 | R104: 31891 | S104: 33503 | T104: 35748 | U104: 34386 | V104: 41054 | W104: 41167 | X104: 44904 | Y104: 47360.73
D105: 102, 103 | E105: Actividades de atención de la salud humana y de servicios sociales | F105: 19832 | G105: 21135 | H105: 21684 | I105: 22112 | J105: 22837 | K105: 23573 | L105: 23797 | M105: 24817 | N105: 27055 | O105: 27758 | P105: 29420 | Q105: 30317 | R105: 31891 | S105: 33503 | T105: 35748 | U105: 34386 | V105: 41054 | W105: 41167 | X105: 44904 | Y105: 47360.73
B106: R + S + T | E106: Actividades artísticas, de entretenimiento y recreación y otras actividades de servicios; Actividades de los hogares individuales en calidad de empleadores; actividades no diferenciadas de los hogares individuales como productores de bienes y servicios para uso propio | F106: 12776 | G106: 13424 | H106: 14135 | I106: 14558 | J106: 14897 | K106: 15259 | L106: 16188 | M106: 16677 | N106: 17718 | O106: 18210 | P106: 18982 | Q106: 20034 | R106: 20456 | S106: 20925 | T106: 23653 | U106: 20865 | V106: 28048 | W106: 35932 | X106: 39690 | Y106: 42953.63
...

Sheet Deflactores
B1: 2005 | C1: 2006 | D1: 2007 | E1: 2008 | F1: 2009 | G1: 2010 | H1: 2011 | I1: 2012 | J1: 2013 | K1: 2014 | L1: 2015 | M1: 2016 | N1: 2017 | O1: 2018 | P1: 2019 | Q1: 2020 | R1: 2021 | S1: 2022 | T1: 2023p | U1: 2024pr
A2: Agricultura, ganadería, caza, silvicultura y pesca | B2: =+'Cuadro 1'!F14/'Cuadro 2'!F13*100 -> 67.105437 | C2: =+'Cuadro 1'!G14/'Cuadro 2'!G13*100 -> 70.834517 | D2: =+'Cuadro 1'!H14/'Cuadro 2'!H13*100 -> 73.846269 | E2: =+'Cuadro 1'!I14/'Cuadro 2'!I13*100 -> 79.842165 | F2: =+'Cuadro 1'!J14/'Cuadro 2'!J13*100 -> 84.259957 | G2: =+'Cuadro 1'!K14/'Cuadro 2'!K13*100 -> 86.150264 | H2: =+'Cuadro 1'!L14/'Cuadro 2'!L13*100 -> 92.637449 | I2: =+'Cuadro 1'!M14/'Cuadro 2'!M13*100 -> 89.176753 | ... U2: =+'Cuadro 1'!Y14/'Cuadro 2'!Y13*100 -> 251.19409
A3: Agricultura, ganadería, caza, silvicultura y pesca | B3: =+'Cuadro 1'!F15/'Cuadro 2'!F14*100 -> 67.105437 | C3: =+'Cuadro 1'!G15/'Cuadro 2'!G14*100 -> 70.834517 | D3: =+'Cuadro 1'!H15/'Cuadro 2'!H14*100 -> 73.846269 | E3: =+'Cuadro 1'!I15/'Cuadro 2'!I14*100 -> 79.842165 | F3: =+'Cuadro 1'!J15/'Cuadro 2'!J14*100 -> 84.259957 | G3: =+'Cuadro 1'!K15/'Cuadro 2'!K14*100 -> 86.150264 | H3: =+'Cuadro 1'!L15/'Cuadro 2'!L14*100 -> 92.637449 | I3: =+'Cuadro 1'!M15/'Cuadro 2'!M14*100 -> 89.176753 | ... U3: =+'Cuadro 1'!Y15/'Cuadro 2'!Y14*100 -> 251.19408
A4: Cultivos agrícolas transitorios; otros cultivos agrícolas permanentes; Propagación de plantas (actividades de viveros, excepto viveros forestales); actividades de apoyo a la agricultura y la ganadería, y posteriores a la cosecha, explotación mixta (agrícola y pecuaria) y caza ordinaria y mediante trampas y actividades de servicios conexas | B4: =+'Cuadro 1'!F16/'Cuadro 2'!F15*100 -> 60.94122 | C4: =+'Cuadro 1'!G16/'Cuadro 2'!G15*100 -> 66.685075 | D4: =+'Cuadro 1'!H16/'Cuadro 2'!H15*100 -> 69.26646 | E4: =+'Cuadro 1'!I16/'Cuadro 2'!I15*100 -> 76.941134 | F4: =+'Cuadro 1'!J16/'Cuadro 2'!J15*100 -> 80.320902 | G4: =+'Cuadro 1'!K16/'Cuadro 2'!K15*100 -> 81.585969 | H4: =+'Cuadro 1'!L16/'Cuadro 2'!L15*100 -> 88.408142 | I4: =+'Cuadro 1'!M16/'Cuadro 2'!M15*100 -> 84.794187 | ... U4: =+'Cuadro 1'!Y16/'Cuadro 2'!Y15*100 -> 265.0874
A5: Cultivo permanente de café | B5: =+'Cuadro 1'!F17/'Cuadro 2'!F16*100 -> 71.859558 | C5: =+'Cuadro 1'!G17/'Cuadro 2'!G16*100 -> 73.176017 | D5: =+'Cuadro 1'!H17/'Cuadro 2'!H16*100 -> 73.685424 | E5: =+'Cuadro 1'!I17/'Cuadro 2'!I16*100 -> 79.053374 | F5: =+'Cuadro 1'!J17/'Cuadro 2'!J16*100 -> 97.390737 | G5: =+'Cuadro 1'!K17/'Cuadro 2'!K16*100 -> 111.56662 | H5: =+'Cuadro 1'!L17/'Cuadro 2'!L16*100 -> 142.08679 | I5: =+'Cuadro 1'!M17/'Cuadro 2'!M16*100 -> 106.13177 | ... U5: =+'Cuadro 1'!Y17/'Cuadro 2'!Y16*100 -> 360.0117
A6: Ganadería | B6: =+'Cuadro 1'!F18/'Cuadro 2'!F17*100 -> 79.56782 | C6: =+'Cuadro 1'!G18/'Cuadro 2'!G17*100 -> 80.060364 | D6: =+'Cuadro 1'!H18/'Cuadro 2'!H17*100 -> 85.046553 | E6: =+'Cuadro 1'!I18/'Cuadro 2'!I17*100 -> 88.960392 | F6: =+'Cuadro 1'!J18/'Cuadro 2'!J17*100 -> 91.333212 | G6: =+'Cuadro 1'!K18/'Cuadro 2'!K17*100 -> 91.093377 | H6: =+'Cuadro 1'!L18/'Cuadro 2'!L17*100 -> 91.575608 | I6: =+'Cuadro 1'!M18/'Cuadro 2'!M17*100 -> 95.185376 | ... U6: =+'Cuadro 1'!Y18/'Cuadro 2'!Y17*100 -> 193.90279
A7: Silvicultura y extracción de madera | B7: =+'Cuadro 1'!F19/'Cuadro 2'!F18*100 -> 64.114114 | C7: =+'Cuadro 1'!G19/'Cuadro 2'!G18*100 -> 67.727609 | D7: =+'Cuadro 1'!H19/'Cuadro 2'!H18*100 -> 72.035139 | E7: =+'Cuadro 1'!I19/'Cuadro 2'!I18*100 -> 73.957571 | F7: =+'Cuadro 1'!J19/'Cuadro 2'!J18*100 -> 79.555237 | G7: =+'Cuadro 1'!K19/'Cuadro 2'!K18*100 -> 79.198876 | H7: =+'Cuadro 1'!L19/'Cuadro 2'!L18*100 -> 80.120482 | I7: =+'Cuadro 1'!M19/'Cuadro 2'!M18*100 -> 84.871312 | ... U7: =+'Cuadro 1'!Y19/'Cuadro 2'!Y18*100 -> 186.72386
A8: Pesca y acuicultura | B8: =+'Cuadro 1'!F20/'Cuadro 2'!F19*100 -> 53.27476 | C8: =+'Cuadro 1'!G20/'Cuadro 2'!G19*100 -> 56.315007 | D8: =+'Cuadro 1'!H20/'Cuadro 2'!H19*100 -> 57.524613 | E8: =+'Cuadro 1'!I20/'Cuadro 2'!I19*100 -> 59.037801 | F8: =+'Cuadro 1'!J20/'Cuadro 2'!J19*100 -> 64.782609 | G8: =+'Cuadro 1'!K20/'Cuadro 2'!K19*100 -> 65.731167 | H8: =+'Cuadro 1'!L20/'Cuadro 2'!L19*100 -> 66.74025 | I8: =+'Cuadro 1'!M20/'Cuadro 2'!M19*100 -> 69.323843 | ... U8: =+'Cuadro 1'!Y20/'Cuadro 2'!Y19*100 -> 231.99153
A9: Explotación de minas y canteras | B9: =+'Cuadro 1'!F21/'Cuadro 2'!F20*100 -> 80.462997 | C9: =+'Cuadro 1'!G21/'Cuadro 2'!G20*100 -> 93.114509 | D9: =+'Cuadro 1'!H21/'Cuadro 2'!H20*100 -> 92.99782 | E9: =+'Cuadro 1'!I21/'Cuadro 2'!I20*100 -> 124.35291 | F9: =+'Cuadro 1'!J21/'Cuadro 2'!J20*100 -> 107.42953 | G9: =+'Cuadro 1'!K21/'Cuadro 2'!K20*100 -> 122.58308 | H9: =+'Cuadro 1'!L21/'Cuadro 2'!L20*100 -> 160.43116 | I9: =+'Cuadro 1'!M21/'Cuadro 2'!M20*100 -> 160.9086 | ... U9: =+'Cuadro 1'!Y21/'Cuadro 2'!Y20*100 -> 207.59472
A10: Explotación de minas y canteras | B10: =+'Cuadro 1'!F22/'Cuadro 2'!F21*100 -> 80.462997 | C10: =+'Cuadro 1'!G22/'Cuadro 2'!G21*100 -> 93.114509 | D10: =+'Cuadro 1'!H22/'Cuadro 2'!H21*100 -> 92.99782 | E10: =+'Cuadro 1'!I22/'Cuadro 2'!I21*100 -> 124.35291 | F10: =+'Cuadro 1'!J22/'Cuadro 2'!J21*100 -> 107.42953 | G10: =+'Cuadro 1'!K22/'Cuadro 2'!K21*100 -> 122.58308 | H10: =+'Cuadro 1'!L22/'Cuadro 2'!L21*100 -> 160.43116 | I10: =+'Cuadro 1'!M22/'Cuadro 2'!M21*100 -> 160.9086 | ... U10: =+'Cuadro 1'!Y22/'Cuadro 2'!Y21*100 -> 207.59472
A11: Extracción de carbón de piedra y lignito | B11: =+'Cuadro 1'!F23/'Cuadro 2'!F22*100 -> 80.494595 | C11: =+'Cuadro 1'!G23/'Cuadro 2'!G22*100 -> 84.243946 | D11: =+'Cuadro 1'!H23/'Cuadro 2'!H22*100 -> 77.030387 | E11: =+'Cuadro 1'!I23/'Cuadro 2'!I22*100 -> 112.30607 | F11: =+'Cuadro 1'!J23/'Cuadro 2'!J22*100 -> 113.61837 | G11: =+'Cuadro 1'!K23/'Cuadro 2'!K22*100 -> 111.65652 | H11: =+'Cuadro 1'!L23/'Cuadro 2'!L22*100 -> 127.08592 | I11: =+'Cuadro 1'!M23/'Cuadro 2'!M22*100 -> 119.2847 | ... U11: =+'Cuadro 1'!Y23/'Cuadro 2'!Y22*100 -> 275.26206
A12: Extracción de petróleo crudo y gas natural y actividades de apoyo para la extracción de petróleo y de gas natural | B12: =+'Cuadro 1'!F24/'Cuadro 2'!F23*100 -> 85.503715 | C12: =+'Cuadro 1'!G24/'Cuadro 2'!G23*100 -> 97.831281 | D12: =+'Cuadro 1'!H24/'Cuadro 2'!H23*100 -> 94.861612 | E12: =+'Cuadro 1'!I24/'Cuadro 2'!I23*100 -> 137.21805 | F12: =+'Cuadro 1'!J24/'Cuadro 2'!J23*100 -> 110.58099 | G12: =+'Cuadro 1'!K24/'Cuadro 2'!K23*100 -> 130.18541 | H12: =+'Cuadro 1'!L24/'Cuadro 2'!L23*100 -> 177.51078 | I12: =+'Cuadro 1'!M24/'Cuadro 2'!M23*100 -> 182.0046 | ... U12: =+'Cuadro 1'!Y24/'Cuadro 2'!Y23*100 -> 175.98633
A13: Extracción de minerales metalíferos | B13: =+'Cuadro 1'!F25/'Cuadro 2'!F24*100 -> 51.5516 | C13: =+'Cuadro 1'!G25/'Cuadro 2'!G24*100 -> 80.328673 | D13: =+'Cuadro 1'!H25/'Cuadro 2'!H24*100 -> 104.3036 | E13: =+'Cuadro 1'!I25/'Cuadro 2'!I24*100 -> 75.713486 | F13: =+'Cuadro 1'!J25/'Cuadro 2'!J24*100 -> 71.729756 | G13: =+'Cuadro 1'!K25/'Cuadro 2'!K24*100 -> 93.195337 | H13: =+'Cuadro 1'!L25/'Cuadro 2'!L24*100 -> 119.1535 | I13: =+'Cuadro 1'!M25/'Cuadro 2'!M24*100 -> 107.26534 | ... U13: =+'Cuadro 1'!Y25/'Cuadro 2'!Y24*100 -> 328.76536
... A107: Gasto de consumo final individual de los hogares; gasto de consumo final de las ISFLH1 | B107: =+'Cuadro 1'!F119/'Cuadro 2'!F118*100 -> 65.769726 | C107: =+'Cuadro 1'!G119/'Cuadro 2'!G118*100 -> 69.298806 | D107: =+'Cuadro 1'!H119/'Cuadro 2'!H118*100 -> 72.687667 | E107: =+'Cuadro 1'!I119/'Cuadro 2'!I118*100 -> 76.525906 | F107: =+'Cuadro 1'!J119/'Cuadro 2'!J118*100 -> 79.708331 | G107: =+'Cuadro 1'!K119/'Cuadro 2'!K118*100 -> 81.582155 | H107: =+'Cuadro 1'!L119/'Cuadro 2'!L118*100 -> 86.166578 | I107: =+'Cuadro 1'!M119/'Cuadro 2'!M118*100 -> 89.269957 | ... U107: =+'Cuadro 1'!Y119/'Cuadro 2'!Y118*100 -> 165.10551
A108: Gasto de consumo final individual de los hogares | B108: =+'Cuadro 1'!F120/'Cuadro 2'!F119*100 -> 65.76505 | C108: =+'Cuadro 1'!G120/'Cuadro 2'!G119*100 -> 69.296591 | D108: =+'Cuadro 1'!H120/'Cuadro 2'!H119*100 -> 72.683562 | E108: =+'Cuadro 1'!I120/'Cuadro 2'!I119*100 -> 76.518 | F108: =+'Cuadro 1'!J120/'Cuadro 2'!J119*100 -> 79.707179 | G108: =+'Cuadro 1'!K120/'Cuadro 2'!K119*100 -> 81.58149 | H108: =+'Cuadro 1'!L120/'Cuadro 2'!L119*100 -> 86.174268 | I108: =+'Cuadro 1'!M120/'Cuadro 2'!M119*100 -> 89.279194 | ... T108: =+'Cuadro 1'!X120/'Cuadro 2'!X119*100 -> 156.78763
A109: Gasto de consumo final de las ISFLH | B109: =+'Cuadro 1'!F121/'Cuadro 2'!F120*100 -> 67.226219 | C109: =+'Cuadro 1'!G121/'Cuadro 2'!G120*100 -> 70.119803 | D109: =+'Cuadro 1'!H121/'Cuadro 2'!H120*100 -> 74.014221 | E109: =+'Cuadro 1'!I121/'Cuadro 2'!I120*100 -> 78.8761 | F109: =+'Cuadro 1'!J121/'Cuadro 2'!J120*100 -> 80.474041 | G109: =+'Cuadro 1'!K121/'Cuadro 2'!K120*100 -> 82.215122 | H109: =+'Cuadro 1'!L121/'Cuadro 2'!L120*100 -> 85.037175 | I109: =+'Cuadro 1'!M121/'Cuadro 2'!M120*100 -> 87.82921 | ... T109: =+'Cuadro 1'!X121/'Cuadro 2'!X120*100 -> 169.57658
A110: Gasto de consumo final del gobierno general | B110: =+'Cuadro 1'!F122/'Cuadro 2'!F121*100 -> 67.020959 | C110: =+'Cuadro 1'!G122/'Cuadro 2'!G121*100 -> 71.537194 | D110: =+'Cuadro 1'!H122/'Cuadro 2'!H121*100 -> 75.986413 | E110: =+'Cuadro 1'!I122/'Cuadro 2'!I121*100 -> 77.269812 | F110: =+'Cuadro 1'!J122/'Cuadro 2'!J121*100 -> 81.528407 | G110: =+'Cuadro 1'!K122/'Cuadro 2'!K121*100 -> 83.775164 | H110: =+'Cuadro 1'!L122/'Cuadro 2'!L121*100 -> 86.846171 | I110: =+'Cuadro 1'!M122/'Cuadro 2'!M121*100 -> 90.062672 | ... U110: =+'Cuadro 1'!Y122/'Cuadro 2'!Y121*100 -> 158.8249
A111: Formación bruta de capital | B111: =+'Cuadro 1'!F124/'Cuadro 2'!F123*100 -> 84.39691 | C111: =+'Cuadro 1'!G124/'Cuadro 2'!G123*100 -> 86.32316 | D111: =+'Cuadro 1'!H124/'Cuadro 2'!H123*100 -> 85.589828 | E111: =+'Cuadro 1'!I124/'Cuadro 2'!I123*100 -> 88.252791 | F111: =+'Cuadro 1'!J124/'Cuadro 2'!J123*100 -> 91.883425 | G111: =+'Cuadro 1'!K124/'Cuadro 2'!K123*100 -> 90.559151 | H111: =+'Cuadro 1'!L124/'Cuadro 2'!L123*100 -> 91.335369 | I111: =+'Cuadro 1'!M124/'Cuadro 2'!M123*100 -> 91.879065 | ... U111: =+'Cuadro 1'!Y124/'Cuadro 2'!Y123*100 -> 163.76937
A112: Formación bruta de capital fijo | B112: =+'Cuadro 1'!F125/'Cuadro 2'!F124*100 -> 82.411739 | C112: =+'Cuadro 1'!G125/'Cuadro 2'!G124*100 -> 84.409719 | D112: =+'Cuadro 1'!H125/'Cuadro 2'!H124*100 -> 84.310265 | E112: =+'Cuadro 1'!I125/'Cuadro 2'!I124*100 -> 87.720286 | F112: =+'Cuadro 1'!J125/'Cuadro 2'!J124*100 -> 91.344066 | G112: =+'Cuadro 1'!K125/'Cuadro 2'!K124*100 -> 90.042721 | H112: =+'Cuadro 1'!L125/'Cuadro 2'!L124*100 -> 90.773081 | I112: =+'Cuadro 1'!M125/'Cuadro 2'!M124*100 -> 91.17051 | ... U112: =+'Cuadro 1'!Y125/'Cuadro 2'!Y124*100 -> 164.66692
A113: Vivienda | B113: =+'Cuadro 1'!F126/'Cuadro 2'!F125*100 -> 39.136454 | C113: =+'Cuadro 1'!G126/'Cuadro 2'!G125*100 -> 40.552065 | D113: =+'Cuadro 1'!H126/'Cuadro 2'!H125*100 -> 44.630346 | E113: =+'Cuadro 1'!I126/'Cuadro 2'!I125*100 -> 52.983633 | F113: =+'Cuadro 1'!J126/'Cuadro 2'!J125*100 -> 59.100385 | G113: =+'Cuadro 1'!K126/'Cuadro 2'!K125*100 -> 61.890802 | H113: =+'Cuadro 1'!L126/'Cuadro 2'!L125*100 -> 67.627937 | I113: =+'Cuadro 1'!M126/'Cuadro 2'!M125*100 -> 83.906734 | ... U113: =+'Cuadro 1'!Y126/'Cuadro 2'!Y125*100 -> 189.10296
A114: Otros edificios y estructuras | B114: =+'Cuadro 1'!F127/'Cuadro 2'!F126*100 -> 69.320122 | C114: =+'Cuadro 1'!G127/'Cuadro 2'!G126*100 -> 72.000927 | D114: =+'Cuadro 1'!H127/'Cuadro 2'!H126*100 -> 76.324585 | E114: =+'Cuadro 1'!I127/'Cuadro 2'!I126*100 -> 84.747932 | F114: =+'Cuadro 1'!J127/'Cuadro 2'!J126*100 -> 86.321071 | G114: =+'Cuadro 1'!K127/'Cuadro 2'!K126*100 -> 86.625817 | H114: =+'Cuadro 1'!L127/'Cuadro 2'!L126*100 -> 90.700488 | I114: =+'Cuadro 1'!M127/'Cuadro 2'!M126*100 -> 90.039796 | ... U114: =+'Cuadro 1'!Y127/'Cuadro 2'!Y126*100 -> 161.87579
A115: Maquinaria y equipo; sistemas de armamento | B115: =+'Cuadro 1'!F128/'Cuadro 2'!F127*100 -> 124.94509 | C115: =+'Cuadro 1'!G128/'Cuadro 2'!G127*100 -> 126.24565 | D115: =+'Cuadro 1'!H128/'Cuadro 2'!H127*100 -> 116.65225 | E115: =+'Cuadro 1'!I128/'Cuadro 2'!I127*100 -> 109.27932 | F115: =+'Cuadro 1'!J128/'Cuadro 2'!J127*100 -> 112.96282 | G115: =+'Cuadro 1'!K128/'Cuadro 2'!K127*100 -> 105.49986 | H115: =+'Cuadro 1'!L128/'Cuadro 2'!L127*100 -> 99.114761 | I115: =+'Cuadro 1'!M128/'Cuadro 2'!M127*100 -> 93.211533 | ... U115: =+'Cuadro 1'!Y128/'Cuadro 2'!Y127*100 -> 139.48016
A116: Recursos biológicos cultivados | B116: =+'Cuadro 1'!F129/'Cuadro 2'!F128*100 -> 65.560166 | C116: =+'Cuadro 1'!G129/'Cuadro 2'!G128*100 -> 65.191003 | D116: =+'Cuadro 1'!H129/'Cuadro 2'!H128*100 -> 72.900901 | E116: =+'Cuadro 1'!I129/'Cuadro 2'!I128*100 -> 85.729462 | F116: =+'Cuadro 1'!J129/'Cuadro 2'!J128*100 -> 96.318212 | G116: =+'Cuadro 1'!K129/'Cuadro 2'!K128*100 -> 98.688839 | H116: =+'Cuadro 1'!L129/'Cuadro 2'!L128*100 -> 97.699166 | I116: =+'Cuadro 1'!M129/'Cuadro 2'!M128*100 -> 88.685575 | ... U116: =+'Cuadro 1'!Y129/'Cuadro 2'!Y128*100 -> 405.69507
A117: Productos de propiedad intelectual | B117: =+'Cuadro 1'!F130/'Cuadro 2'!F129*100 -> 89.271109 | C117: =+'Cuadro 1'!G130/'Cuadro 2'!G129*100 -> 93.348683 | D117: =+'Cuadro 1'!H130/'Cuadro 2'!H129*100 -> 88.257576 | E117: =+'Cuadro 1'!I130/'Cuadro 2'!I129*100 -> 102.87798 | F117: =+'Cuadro 1'!J130/'Cuadro 2'!J129*100 -> 101.80213 | G117: =+'Cuadro 1'!K130/'Cuadro 2'!K129*100 -> 108.57671 | H117: =+'Cuadro 1'!L130/'Cuadro 2'!L129*100 -> 120.12424 | I117: =+'Cuadro 1'!M130/'Cuadro 2'!M129*100 -> 109.53534 | ... U117: =+'Cuadro 1'!Y130/'Cuadro 2'!Y129*100 -> 167.28349
A118: Variación de existencias2
A119: Adquisición menos disposición de objetos valiosos | B119: =+'Cuadro 1'!F132/'Cuadro 2'!F131*100 -> 142.85714 | C119: =+'Cuadro 1'!G132/'Cuadro 2'!G131*100 -> 125 | D119: =+'Cuadro 1'!H132/'Cuadro 2'!H131*100 -> 116.66667 | E119: =+'Cuadro 1'!I132/'Cuadro 2'!I131*100 -> 105.26316 | F119: =+'Cuadro 1'!J132/'Cuadro 2'!J131*100 -> 110.52632 | G119: =+'Cuadro 1'!K132/'Cuadro 2'!K131*100 -> 100 | H119: =+'Cuadro 1'!L132/'Cuadro 2'!L131*100 -> 91.304348 | I119: =+'Cuadro 1'!M132/'Cuadro 2'!M131*100 -> 92 | ... T119: =+'Cuadro 1'!X132/'Cuadro 2'!X131*100 -> 120.83333
A120: Exportaciones | B120: =+'Cuadro 1'!F133/'Cuadro 2'!F132*100 -> 65.083688 | C120: =+'Cuadro 1'!G133/'Cuadro 2'!G132*100 -> 70.097293 | D120: =+'Cuadro 1'!H133/'Cuadro 2'!H132*100 -> 68.68879 | E120: =+'Cuadro 1'!I133/'Cuadro 2'!I132*100 -> 82.503537 | F120: =+'Cuadro 1'!J133/'Cuadro 2'!J132*100 -> 83.080538 | G120: =+'Cuadro 1'!K133/'Cuadro 2'!K132*100 -> 87.847198 | H120: =+'Cuadro 1'!L133/'Cuadro 2'!L132*100 -> 105.0331 | I120: =+'Cuadro 1'!M133/'Cuadro 2'!M132*100 -> 105.63485 | ... U120: =+'Cuadro 1'!Y133/'Cuadro 2'!Y132*100 -> 194.4136
A121: Importaciones | B121: =+'Cuadro 1'!F134/'Cuadro 2'!F133*100 -> 87.815724 | C121: =+'Cuadro 1'!G134/'Cuadro 2'!G133*100 -> 90.278003 | D121: =+'Cuadro 1'!H134/'Cuadro 2'!H133*100 -> 83.968481 | E121: =+'Cuadro 1'!I134/'Cuadro 2'!I133*100 -> 84.574737 | F121: =+'Cuadro 1'!J134/'Cuadro 2'!J133*100 -> 86.676507 | G121: =+'Cuadro 1'!K134/'Cuadro 2'!K133*100 -> 81.17269 | H121: =+'Cuadro 1'!L134/'Cuadro 2'!L133*100 -> 86.546983 | I121: =+'Cuadro 1'!M134/'Cuadro 2'!M133*100 -> 84.481285 | ... U121: =+'Cuadro 1'!Y134/'Cuadro 2'!Y133*100 -> 149.45702
A122: Producto interno bruto | B122: =+'Cuadro 1'!F135/'Cuadro 2'!F134*100 -> 65.641649 | C122: =+'Cuadro 1'!G135/'Cuadro 2'!G134*100 -> 69.453894 | D122: =+'Cuadro 1'!H135/'Cuadro 2'!H134*100 -> 73.066909 | E122: =+'Cuadro 1'!I135/'Cuadro 2'!I134*100 -> 78.676535 | F122: =+'Cuadro 1'!J135/'Cuadro 2'!J134*100 -> 81.874127 | G122: =+'Cuadro 1'!K135/'Cuadro 2'!K134*100 -> 84.989323 | H122: =+'Cuadro 1'!L135/'Cuadro 2'!L134*100 -> 90.417424 | I122: =+'Cuadro 1'!M135/'Cuadro 2'!M134*100 -> 93.68751 | ... U122: =+'Cuadro 1'!Y135/'Cuadro 2'!Y134*100 -> 171.46078
