Workbook

Sheet K
A1: Producto interno bruto por actividad económica, volumen a precios año anterior encadenado, series empalmadas, referencia 2018 (miles de millones de pesos encadenados)
A3: Unidad | B3: Miles de millones de pesos
A4: Frecuencia | B4: TRIMESTRAL
A5: Fuente | B5: Banco Central de Chile
A6: Desfase publicación | B6: 48 días terminado el trimestre
A7: Última actualización | B7: 18-08-2025
A8: Primera observación | B8: 01-01-1996
A9: Última observación | B9: 01-04-2025
A10: Contacto | B10: contactocentral.bcentral.cl https://contactocentral.bcentral.cl/
A11: Metodología | B11: Cuentas Nacionales https://www.bcentral.cl/web/banco-central/cuentas-nacionales-trimestrales-doc-de-interes
A12: Notas | B12: Se consideran cifras preliminares a las correspondendientes a los años (t) y (t-1), siendo (t) el año en curso. El volumen a precios del año anterior encadenado es obtenido del índice promedio de 2018 que se iguala al valor nominal de la serie de dicho año. Las series encadenadas pierden la propiedad de aditividad que presentan las series en base fija, por lo cual los agregados difieren de la suma de sus componentes. Para mayores detalles acerca de la metodología de encadenamiento, ver Estudios Estadísticos Económicos N° 90, disponible en www.bcentral.cl Los Servicios personales incluye educación, salud y otros servicios. La serie de PIB no minero corresponde al PIB, excluyendo la actividad minería. NC: No corresponde cálculo dado que uno de los valores para la determinación de la variación, es negativa.
A14: Reg | B14: Descripción series | C14: 41275 | D14: 41640 | E14: 42005 | F14: 42370 | G14: 42736 | H14: 43101 | I14: 43466 | J14: 43831 | K14: 44197 | L14: 44562 | M14: 44927 | N14: 45292
A15: 1. | B15: Agropecuario-silvícola | C15: 5492.6363 | D15: 5282.6666 | E15: 5662.9272 | F15: 5916.7396 | G15: 5877.0272 | H15: 6049.7803 | I15: 5988.5003 | J15: 6032.5659 | K15: 6254.6177 | L15: 6228.7957 | M15: 6117.1851 | N15: 6569.9498
A16: 2. | B16: Pesca | C16: 1109.3295 | D16: 1216.6188 | E16: 1070.4623 | F16: 993.17886 | G16: 1298.1539 | H16: 1390.1527 | I16: 1397.8822 | J16: 1169.575 | K16: 1221.8785 | L16: 1239.2427 | M16: 1287.5614 | N16: 1233.1056
A17: 3. | B17: Minería | C17: 16576.585 | D17: 16946.741 | E17: 16727.391 | F17: 16202.944 | G17: 15870.255 | H17: 16825.436 | I17: 16062.136 | J17: 16185.354 | K17: 15456.019 | L17: 14459.467 | M17: 14462.749 | N17: 15209.636
A18: 3.1. | B18: Minería del cobre | C18: 14641.87 | D18: 14976.177 | E18: 14840.462 | F18: 14277.976 | G18: 14068.641 | H18: 14971.528 | I18: 14243.801 | J18: 14208.615 | K18: 13335.853 | L18: 12196.153 | M18: 11682.516 | N18: 12308.887
A19: 3.2. | B19: Otras actividades mineras | C19: 1929.6317 | D19: 1965.2138 | E19: 1869.1716 | F19: 1923.8492 | G19: 1807.5859 | H19: 1853.9075 | I19: 1818.3354 | J19: 1978.642 | K19: 2185.8832 | L19: 2479.2725 | M19: 2753.6956 | N19: 2878.5319
A20: 4. | B20: Industria Manufacturera | C20: 16798.489 | D20: 16882.1 | E20: 17144.527 | F20: 17128.83 | G20: 17290.702 | H20: 18193.73 | I20: 17867.707 | J20: 17477.143 | K20: 18474.257 | L20: 18019.546 | M20: 18551.757 | N20: 19061.677
A21: 4.1. | B21: Alimentos, bebidas y tabaco | C21: 5951.2547 | D21: 5998.3097 | E21: 6408.5488 | F21: 6226.0531 | G21: 6383.2687 | H21: 7065.8635 | I21: 6803.3545 | J21: 6671.3831 | K21: 6951.131 | L21: 7002.8001 | M21: 7234.2002 | N21: 7369.8349
A22: 4.1.1. | B22: Alimentos | C22: 4456.7826 | D22: 4703.1195 | E22: 4739.306 | F22: 4767.6721 | G22: 4979.2039 | H22: 5286.0533 | I22: 5199.6511 | J22: 5210.7082 | K22: 5195.5336 | L22: 5301.6164 | M22: 5468.8864 | N22: 5661.8488
A23: 4.1.2. | B23: Bebidas y tabaco | C23: 1483.3562 | D23: 1304.2514 | E23: 1638.4647 | F23: 1441.6619 | G23: 1386.3937 | H23: 1779.8101 | I23: 1603.7034 | J23: 1470.7902 | K23: 1735.4214 | L23: 1683.2442 | M23: 1748.8231 | N23: 1676.4392
A24: 4.2. | B24: Textil, prendas de vestir, cuero y calzado | C24: 335.44997 | D24: 308.26189 | E24: 303.94411 | F24: 293.14727 | G24: 304.17524 | H24: 291.00293 | I24: 283.51924 | J24: 263.11204 | K24: 317.54354 | L24: 321.86297 | M24: 365.01785 | N24: 351.84901
A25: 4.3. | B25: Maderas y muebles | C25: 996.70456 | D25: 1070.3288 | E25: 1131.5819 | F25: 1167.003 | G25: 1168.5835 | H25: 1220.2064 | I25: 1146.4571 | J25: 1055.61 | K25: 1078.4196 | L25: 1006.265 | M25: 929.41855 | N25: 965.03677
... A46: 17. | B46: PIB no minero | C46: 153510.86 | D46: 156184.45 | E46: 160155.65 | F46: 163638.79 | G46: 166306.47 | H46: 172609.43 | I46: 174574.44 | J46: 162776.17 | K46: 184568.43 | L46: 191143.15 | M46: 192286.83 | N46: 196805.36

Sheet M
A1: Producto interno bruto por clase de actividad económica, a precios corrientes, series empalmadas, referencia 2018 (miles de millones de pesos)
A3: Unidad | B3: Miles de millones de pesos
A4: Frecuencia | B4: TRIMESTRAL
A5: Fuente | B5: Banco Central de Chile
A6: Desfase publicación | B6: 48 días terminado el trimestre
A7: Última actualización | B7: 18-08-2025
A8: Primera observación | B8: 01-01-1996
A9: Última observación | B9: 01-04-2025
A10: Contacto | B10: contactocentral.bcentral.cl https://contactocentral.bcentral.cl/
A11: Metodología | B11: Cuentas Nacionales https://www.bcentral.cl/web/banco-central/cuentas-nacionales-trimestrales-doc-de-interes
A12: Notas | B12: Se consideran cifras preliminares a las correspondendientes a los años (t) y (t-1), siendo (t) el año en curso. Los Servicios personales incluye educación, salud y otros servicios. NC: No corresponde cálculo dado que uno de los valores para la determinación de la variación, es negativa.
A14: Reg | B14: Descripción series | C14: 41275 | D14: 41640 | E14: 42005 | F14: 42370 | G14: 42736 | H14: 43101 | I14: 43466 | J14: 43831 | K14: 44197 | L14: 44562 | M14: 44927 | N14: 45292
A15: 1. | B15: Agropecuario-silvícola | C15: 4235.1985 | D15: 4685.2542 | E15: 5284.4807 | F15: 6075.5145 | G15: 6155.7591 | H15: 6049.7803 | I15: 6228.0024 | J15: 7202.2419 | K15: 7261.0424 | L15: 6929.6401 | M15: 8506.3763 | N15: 10617.403
A16: 2. | B16: Pesca | C16: 534.06513 | D16: 1153.8219 | E16: 599.484 | F16: 1011.0656 | G16: 1520.6613 | H16: 1390.1527 | I16: 1569.4354 | J16: 939.49292 | K16: 1132.6323 | L16: 1579.6832 | M16: 1331.0907 | N16: 1574.7298
A17: 3. | B17: Minería | C17: 14257.543 | D17: 15064.831 | E17: 12600.328 | F17: 12486.268 | G17: 16096.36 | H17: 16825.436 | I17: 15975.054 | J17: 23314.882 | K17: 33682.151 | L17: 35174.718 | M17: 29486.727 | N17: 36599.962
A18: 3.1. | B18: Minería del cobre | C18: 12627.316 | D18: 13595.983 | E18: 11371.402 | F18: 10884.601 | G18: 14430.219 | H18: 14971.528 | I18: 14187.464 | J18: 21018.892 | K18: 30464.705 | L18: 25427.734 | M18: 22458.655 | N18: 32072.244
A19: 3.2. | B19: Otras actividades mineras | C19: 1630.2268 | D19: 1468.8479 | E19: 1228.9267 | F19: 1601.667 | G19: 1666.1409 | H19: 1853.9075 | I19: 1787.5902 | J19: 2295.9896 | K19: 3217.4455 | L19: 9746.9839 | M19: 7028.0716 | N19: 4527.7181
A20: 4. | B20: Industria manufacturera | C20: 13710.367 | D20: 14677.456 | E20: 16494.981 | F20: 16380.174 | G20: 16426.761 | H20: 18193.73 | I20: 17537.427 | J20: 18105.714 | K20: 20423.684 | L20: 24926.686 | M20: 26512.464 | N20: 28079.404
A21: 4.1. | B21: Alimentos, bebidas y tabaco | C21: 4425.5805 | D21: 4876.788 | E21: 6008.7878 | F21: 5991.2912 | G21: 6175.1572 | H21: 7065.8635 | I21: 7068.6005 | J21: 7417.2973 | K21: 7614.1788 | L21: 9177.8682 | M21: 10464.721 | N21: 11119.379
A22: 4.1.1. | B22: Alimentos | C22: 3234.6586 | D22: 3685.853 | E22: 4366.6221 | F22: 4606.4354 | G22: 4915.6605 | H22: 5286.0533 | I22: 5278.7377 | J22: 5598.0425 | K22: 5655.7552 | L22: 7328.2202 | M22: 8208.0217 | N22: 8844.7701
A23: 4.1.2. | B23: Bebidas y tabaco | C23: 1190.922 | D23: 1190.935 | E23: 1642.1657 | F23: 1384.8558 | G23: 1259.4967 | H23: 1779.8101 | I23: 1789.8628 | J23: 1819.2549 | K23: 1958.4236 | L23: 1849.648 | M23: 2256.6996 | N23: 2274.6089
A24: 4.2. | B24: Textil, prendas de vestir, cuero y calzado | C24: 405.71864 | D24: 355.99462 | E24: 326.81415 | F24: 345.7309 | G24: 339.51998 | H24: 291.00293 | I24: 239.75236 | J24: 188.72697 | K24: 220.29414 | L24: 181.9809 | M24: 254.96965 | N24: 198.88615
A25: 4.3. | B25: Maderas y muebles | C25: 812.79172 | D25: 1071.0982 | E25: 1212.6202 | F25: 1238.8628 | G25: 1196.4158 | H25: 1220.2064 | I25: 1119.3324 | J25: 1170.3695 | K25: 1549.2293 | L25: 1837.1324 | M25: 1209.6644 | N25: 1228.1874
... A45: 16. | B45: PIB a precios corrientes | C45: 137309.19 | D45: 147951.29 | E45: 158622.9 | F45: 168764.69 | G45: 179314.91 | H45: 189434.87 | I45: 195531.72 | J45: 201257.75 | K45: 239418.12 | L45: 263065.44 | M45: 281857.49 | N45: 311630.88

Sheet Deflactores
A2: Descripción series | B2: 41275 | C2: 41640 | D2: 42005 | E2: 42370 | F2: 42736 | G2: 43101 | H2: 43466 | I2: 43831 | J2: 44197 | K2: 44562 | L2: 44927 | M2: 45292
A3: Agropecuario-silvícola | B3: =+M!C15/K!C15*100 -> 77.106843 | C3: =+M!D15/K!D15*100 -> 88.691084 | D3: =+M!E15/K!E15*100 -> 93.317122 | E3: =+M!F15/K!F15*100 -> 102.68349 | F3: =+M!G15/K!G15*100 -> 104.74274 | G3: =+M!H15/K!H15*100 -> 100 | H3: =+M!I15/K!I15*100 -> 103.99937 | I3: =+M!J15/K!J15*100 -> 119.38936 | ... M3: =+M!N15/K!N15*100 -> 161.60554
A4: Pesca | B4: =+M!C16/K!C16*100 -> 48.143058 | C4: =+M!D16/K!D16*100 -> 94.838407 | D4: =+M!E16/K!E16*100 -> 56.002347 | E4: =+M!F16/K!F16*100 -> 101.80096 | F4: =+M!G16/K!G16*100 -> 117.14029 | G4: =+M!H16/K!H16*100 -> 100 | H4: =+M!I16/K!I16*100 -> 112.27237 | I4: =+M!J16/K!J16*100 -> 80.327723 | ... M4: =+M!N16/K!N16*100 -> 127.70437
A5: Minería | B5: =+M!C17/K!C17*100 -> 86.010129 | C5: =+M!D17/K!D17*100 -> 88.895151 | D5: =+M!E17/K!E17*100 -> 75.32752 | E5: =+M!F17/K!F17*100 -> 77.061721 | F5: =+M!G17/K!G17*100 -> 101.42471 | G5: =+M!H17/K!H17*100 -> 100 | H5: =+M!I17/K!I17*100 -> 99.457842 | I5: =+M!J17/K!J17*100 -> 144.04925 | ... M5: =+M!N17/K!N17*100 -> 240.63667
A6: Minería del cobre | B6: =+M!C18/K!C18*100 -> 86.24114 | C6: =+M!D18/K!D18*100 -> 90.78407 | D6: =+M!E18/K!E18*100 -> 76.624311 | E6: =+M!F18/K!F18*100 -> 76.233503 | F6: =+M!G18/K!G18*100 -> 102.5701 | G6: =+M!H18/K!H18*100 -> 100 | H6: =+M!I18/K!I18*100 -> 99.60448 | I6: =+M!J18/K!J18*100 -> 147.93062 | ... M6: =+M!N18/K!N18*100 -> 260.56169
A7: Otras actividades mineras | B7: =+M!C19/K!C19*100 -> 84.483831 | C7: =+M!D19/K!D19*100 -> 74.742396 | D7: =+M!E19/K!E19*100 -> 65.747134 | E7: =+M!F19/K!F19*100 -> 83.253247 | F7: =+M!G19/K!G19*100 -> 92.174926 | G7: =+M!H19/K!H19*100 -> 100 | H7: =+M!I19/K!I19*100 -> 98.309158 | I7: =+M!J19/K!J19*100 -> 116.03865 | ... M7: =+M!N19/K!N19*100 -> 157.29261
A8: Industria manufacturera | B8: =+M!C20/K!C20*100 -> 81.61667 | C8: =+M!D20/K!D20*100 -> 86.94094 | D8: =+M!E20/K!E20*100 -> 96.211354 | E8: =+M!F20/K!F20*100 -> 95.629263 | F8: =+M!G20/K!G20*100 -> 95.003435 | G8: =+M!H20/K!H20*100 -> 100 | H8: =+M!I20/K!I20*100 -> 98.151527 | I8: =+M!J20/K!J20*100 -> 103.59653 | ... M8: =+M!N20/K!N20*100 -> 147.30815
A9: Alimentos, bebidas y tabaco | B9: =+M!C21/K!C21*100 -> 74.363823 | C9: =+M!D21/K!D21*100 -> 81.302705 | D9: =+M!E21/K!E21*100 -> 93.762066 | E9: =+M!F21/K!F21*100 -> 96.229363 | F9: =+M!G21/K!G21*100 -> 96.739735 | G9: =+M!H21/K!H21*100 -> 100 | H9: =+M!I21/K!I21*100 -> 103.89875 | I9: =+M!J21/K!J21*100 -> 111.1808 | ... M9: =+M!N21/K!N21*100 -> 150.87691
A10: Alimentos | B10: =+M!C22/K!C22*100 -> 72.578335 | C10: =+M!D22/K!D22*100 -> 78.370388 | D10: =+M!E22/K!E22*100 -> 92.136318 | E10: =+M!F22/K!F22*100 -> 96.618125 | F10: =+M!G22/K!G22*100 -> 98.723825 | G10: =+M!H22/K!H22*100 -> 100 | H10: =+M!I22/K!I22*100 -> 101.521 | I10: =+M!J22/K!J22*100 -> 107.43343 | ... M10: =+M!N22/K!N22*100 -> 156.217
A11: Bebidas y tabaco | B11: =+M!C23/K!C23*100 -> 80.285638 | C11: =+M!D23/K!D23*100 -> 91.311769 | D11: =+M!E23/K!E23*100 -> 100.22589 | E11: =+M!F23/K!F23*100 -> 96.05968 | F11: =+M!G23/K!G23*100 -> 90.846968 | G11: =+M!H23/K!H23*100 -> 100 | H11: =+M!I23/K!I23*100 -> 111.6081 | I11: =+M!J23/K!J23*100 -> 123.69234 | ... M11: =+M!N23/K!N23*100 -> 135.68097
A12: Textil, prendas de vestir, cuero y calzado | B12: =+M!C24/K!C24*100 -> 120.94759 | C12: =+M!D24/K!D24*100 -> 115.48448 | D12: =+M!E24/K!E24*100 -> 107.52442 | E12: =+M!F24/K!F24*100 -> 117.93761 | F12: =+M!G24/K!G24*100 -> 111.61986 | G12: =+M!H24/K!H24*100 -> 100 | H12: =+M!I24/K!I24*100 -> 84.562993 | I12: =+M!J24/K!J24*100 -> 71.728747 | ... M12: =+M!N24/K!N24*100 -> 56.525995
A13: Maderas y muebles | B13: =+M!C25/K!C25*100 -> 81.547908 | C13: =+M!D25/K!D25*100 -> 100.07188 | D13: =+M!E25/K!E25*100 -> 107.16151 | E13: =+M!F25/K!F25*100 -> 106.15764 | F13: =+M!G25/K!G25*100 -> 102.3817 | G13: =+M!H25/K!H25*100 -> 100 | H13: =+M!I25/K!I25*100 -> 97.634046 | I13: =+M!J25/K!J25*100 -> 110.87139 | ... M13: =+M!N25/K!N25*100 -> 127.26846
A14: Celulosa, papel e imprentas | B14: =+M!C26/K!C26*100 -> 49.854064 | C14: =+M!D26/K!D26*100 -> 59.456559 | D14: =+M!E26/K!E26*100 -> 72.105553 | E14: =+M!F26/K!F26*100 -> 66.424574 | F14: =+M!G26/K!G26*100 -> 76.712844 | G14: =+M!H26/K!H26*100 -> 100 | H14: =+M!I26/K!I26*100 -> 72.66625 | I14: =+M!J26/K!J26*100 -> 65.215368 | ... M14: =+M!N26/K!N26*100 -> 105.80576
... A33: PIB a precios corrientes | B33: =+M!C45/K!C45*100 -> 80.834835 | C33: =+M!D45/K!D45*100 -> 85.566011 | D33: =+M!E45/K!E45*100 -> 89.805263 | E33: =+M!F45/K!F45*100 -> 93.900973 | F33: =+M!G45/K!G45*100 -> 98.434692 | G33: =+M!H45/K!H45*100 -> 100 | H33: =+M!I45/K!I45*100 -> 102.56779 | I33: =+M!J45/K!J45*100 -> 112.48171 | ... M33: =+M!N45/K!N45*100 -> 148.44575

Sheet Deflactor descarga
A1: Deflactor del producto interno bruto por clase de actividad económica, anual, series empalmadas, referencia 2018
A3: Unidad | B3: Índice
A4: Frecuencia | B4: ANUAL
A5: Fuente | B5: Banco Central de Chile
A6: Desfase publicación | B6: 78 días terminado el año
A7: Última actualización | B7: 18-03-2025
A8: Primera observación | B8: 01-01-1996
A9: Última observación | B9: 01-01-2024
A10: Contacto | B10: contactocentral.bcentral.cl https://contactocentral.bcentral.cl/
A11: Metodología | B11: Cuentas Nacionales https://si3.bcentral.cl/estadisticas/Principal1/enlaces/documentos/CCNN/CCNN_CNT.html
A12: Notas | B12: Se consideran cifras preliminares a las correspondendientes a los años (t) y (t-1), siendo (t) el año en curso. Los Servicios personales incluye educación, salud y otros servicios. NC: No corresponde cálculo dado que uno de los valores para la determinación de la variación, es negativa.
A14: Reg | B14: Descripción series | C14: 41275 | D14: 41640 | E14: 42005 | F14: 42370 | G14: 42736 | H14: 43101 | I14: 43466 | J14: 43831 | K14: 44197 | L14: 44562 | M14: 44927 | N14: 45292
A15: 1. | B15: Agropecuario-silvícola | C15: 77.106843 | D15: 88.691084 | E15: 93.317122 | F15: 102.68349 | G15: 104.74274 | H15: 100 | I15: 103.99937 | J15: 119.38936 | K15: 116.09091 | L15: 111.25168 | M15: 139.05704 | N15: 161.60554
A16: 2. | B16: Pesca | C16: 48.143058 | D16: 94.838407 | E16: 56.002347 | F16: 101.80096 | G16: 117.14029 | H16: 100 | I16: 112.27237 | J16: 80.327723 | K16: 92.695985 | L16: 127.47165 | M16: 103.38075 | N16: 127.70437
A17: 3. | B17: Minería | C17: 86.010129 | D17: 88.895151 | E17: 75.32752 | F17: 77.061721 | G17: 101.42471 | H17: 100 | I17: 99.457842 | J17: 144.04925 | K17: 217.92255 | L17: 243.26428 | M17: 203.88051 | N17: 240.63667
A18: 3.1. | B18: Minería del cobre | C18: 86.24114 | D18: 90.78407 | E18: 76.624311 | F18: 76.233503 | G18: 102.5701 | H18: 100 | I18: 99.60448 | J18: 147.93062 | K18: 228.44211 | L18: 208.4898 | M18: 192.24159 | N18: 260.56169
A19: 3.2. | B19: Otras actividades mineras | C19: 84.483831 | D19: 74.742396 | E19: 65.747134 | F19: 83.253247 | G19: 92.174926 | H19: 100 | I19: 98.309158 | J19: 116.03865 | K19: 147.19201 | L19: 393.13887 | M19: 255.22326 | N19: 157.29261
A20: 4. | B20: Industria Manufacturera | C20: 81.61667 | D20: 86.94094 | E20: 96.211354 | F20: 95.629263 | G20: 95.003435 | H20: 100 | I20: 98.151527 | J20: 103.59653 | K20: 110.55212 | L20: 138.33138 | M20: 142.91079 | N20: 147.30815
A21: 4.1. | B21: Alimentos, bebidas y tabaco | C21: 74.363823 | D21: 81.302705 | E21: 93.762066 | F21: 96.229363 | G21: 96.739735 | H21: 100 | I21: 103.89875 | J21: 111.1808 | K21: 109.5387 | L21: 131.05998 | M21: 144.65623 | N21: 150.87691
A22: 4.1.1. | B22: Alimentos | C22: 72.578335 | D22: 78.370388 | E22: 92.136318 | F22: 96.618125 | G22: 98.723825 | H22: 100 | I22: 101.521 | J22: 107.43343 | K22: 108.85802 | L22: 138.22615 | M22: 150.0858 | N22: 156.217
A23: 4.1.2. | B23: Bebidas y tabaco | C23: 80.285638 | D23: 91.311769 | E23: 100.22589 | F23: 96.05968 | G23: 90.846968 | H23: 100 | I23: 111.6081 | J23: 123.69234 | K23: 112.85003 | L23: 109.8859 | M23: 129.04104 | N23: 135.68097
A24: 4.2. | B24: Textil, prendas de vestir, cuero y calzado | C24: 120.94759 | D24: 115.48448 | E24: 107.52442 | F24: 117.93761 | G24: 111.61986 | H24: 100 | I24: 84.562993 | J24: 71.728747 | K24: 69.374467 | L24: 56.53987 | M24: 69.851283 | N24: 56.525995
A25: 4.3. | B25: Maderas y muebles | C25: 81.547908 | D25: 100.07188 | E25: 107.16151 | F25: 106.15764 | G25: 102.3817 | H25: 100 | I25: 97.634046 | J25: 110.87139 | K25: 143.65737 | L25: 182.56945 | M25: 130.15282 | N25: 127.26846
... A44: 15. | B44: Deflactor Producto Interno Bruto | C44: 80.834835 | D44: 85.566011 | E44: 89.805263 | F44: 93.900973 | G44: 98.434692 | H44: 100 | I44: 102.56779 | J44: 112.48171 | K44: 120.20788 | L44: 129.29578 | M44: 137.81349 | N44: 148.44575

Sheet Hoja1
A1: year | B1: deflactor_comercio | C1: deflactor_comunicaciones | D1: def_al
A2: 2013 | B2: 80.469954 | C2: 111.17434
A3: =A2+1 -> 2014 | B3: 87.932105 | C3: 111.42786
A4: =A3+1 -> 2015 | B4: 93.021787 | C4: 110.4288
A5: =A4+1 -> 2016 | B5: 99.27464 | C5: 108.15409
A6: =A5+1 -> 2017 | B6: 101.26878 | C6: 105.31818
A7: =A6+1 -> 2018 | B7: 100 | C7: 100
A8: =A7+1 -> 2019 | B8: 100.87566 | C8: 98.531452
A9: =A8+1 -> 2020 | B9: 107.49939 | C9: 91.363838
A10: =A9+1 -> 2021 | B10: 114.66887 | C10: 92.899946
A11: =A10+1 -> 2022 | B11: 120.37242 | C11: 94.646742
A12: =A11+1 -> 2023 | B12: 132.56552 | C12: 100.2864
A13: =A12+1 -> 2024 | B13: 127.5837 | C13: 106.12099
